[
  {
    "time": 1437663600,
    "open": 110000.0,
    "high": 131800.0,
    "low": 90700.0,
    "close": 114500.0,
    "volume": 2262247.0
  },
  {
    "time": 1437922800,
    "open": 120300.0,
    "high": 123000.0,
    "low": 84500.0,
    "close": 103600.0,
    "volume": 1743098.0
  },
  {
    "time": 1438527600,
    "open": 102800.0,
    "high": 113700.0,
    "low": 98000.0,
    "close": 108000.0,
    "volume": 780208.0
  },
  {
    "time": 1439132400,
    "open": 106300.0,
    "high": 107700.0,
    "low": 91100.0,
    "close": 96800.0,
    "volume": 371497.0
  },
  {
    "time": 1439737200,
    "open": 97300.0,
    "high": 97300.0,
    "low": 81100.0,
    "close": 84600.0,
    "volume": 300629.0
  },
  {
    "time": 1440342000,
    "open": 79700.0,
    "high": 82700.0,
    "low": 60600.0,
    "close": 78000.0,
    "volume": 1178934.0
  },
  {
    "time": 1440946800,
    "open": 77800.0,
    "high": 79600.0,
    "low": 70400.0,
    "close": 71200.0,
    "volume": 360048.0
  },
  {
    "time": 1441551600,
    "open": 68800.0,
    "high": 72400.0,
    "low": 64900.0,
    "close": 70100.0,
    "volume": 322141.0
  },
  {
    "time": 1442156400,
    "open": 70800.0,
    "high": 82000.0,
    "low": 68800.0,
    "close": 81000.0,
    "volume": 642770.0
  },
  {
    "time": 1442761200,
    "open": 80000.0,
    "high": 89100.0,
    "low": 79100.0,
    "close": 84500.0,
    "volume": 517525.0
  },
  {
    "time": 1443538800,
    "open": 81600.0,
    "high": 83700.0,
    "low": 77400.0,
    "close": 78000.0,
    "volume": 166215.0
  },
  {
    "time": 1443970800,
    "open": 79000.0,
    "high": 81600.0,
    "low": 70000.0,
    "close": 70900.0,
    "volume": 249220.0
  },
  {
    "time": 1444575600,
    "open": 71600.0,
    "high": 72000.0,
    "low": 66900.0,
    "close": 67200.0,
    "volume": 309478.0
  },
  {
    "time": 1445180400,
    "open": 67900.0,
    "high": 74700.0,
    "low": 63400.0,
    "close": 71000.0,
    "volume": 1429836.0
  },
  {
    "time": 1445785200,
    "open": 72000.0,
    "high": 75600.0,
    "low": 71100.0,
    "close": 71500.0,
    "volume": 498426.0
  },
  {
    "time": 1446390000,
    "open": 66200.0,
    "high": 73100.0,
    "low": 60300.0,
    "close": 70000.0,
    "volume": 1081758.0
  },
  {
    "time": 1446994800,
    "open": 68700.0,
    "high": 70300.0,
    "low": 62500.0,
    "close": 68200.0,
    "volume": 560683.0
  },
  {
    "time": 1447599600,
    "open": 66200.0,
    "high": 76300.0,
    "low": 65700.0,
    "close": 75400.0,
    "volume": 748969.0
  },
  {
    "time": 1448204400,
    "open": 75600.0,
    "high": 76700.0,
    "low": 71900.0,
    "close": 74800.0,
    "volume": 440986.0
  },
  {
    "time": 1448809200,
    "open": 74300.0,
    "high": 79500.0,
    "low": 73300.0,
    "close": 75500.0,
    "volume": 426701.0
  },
  {
    "time": 1449414000,
    "open": 76300.0,
    "high": 76400.0,
    "low": 67200.0,
    "close": 68300.0,
    "volume": 380609.0
  },
  {
    "time": 1450018800,
    "open": 67300.0,
    "high": 72000.0,
    "low": 65000.0,
    "close": 71800.0,
    "volume": 239680.0
  },
  {
    "time": 1450623600,
    "open": 71100.0,
    "high": 73500.0,
    "low": 68800.0,
    "close": 69300.0,
    "volume": 194301.0
  },
  {
    "time": 1451228400,
    "open": 69600.0,
    "high": 74000.0,
    "low": 68000.0,
    "close": 73000.0,
    "volume": 198639.0
  },
  {
    "time": 1451833200,
    "open": 73000.0,
    "high": 75700.0,
    "low": 69700.0,
    "close": 75400.0,
    "volume": 536547.0
  },
  {
    "time": 1452438000,
    "open": 75000.0,
    "high": 77700.0,
    "low": 71400.0,
    "close": 72200.0,
    "volume": 560454.0
  },
  {
    "time": 1453042800,
    "open": 70900.0,
    "high": 78300.0,
    "low": 70800.0,
    "close": 76000.0,
    "volume": 800614.0
  },
  {
    "time": 1453647600,
    "open": 77000.0,
    "high": 82800.0,
    "low": 75200.0,
    "close": 82100.0,
    "volume": 818955.0
  },
  {
    "time": 1454252400,
    "open": 83000.0,
    "high": 84300.0,
    "low": 77700.0,
    "close": 80500.0,
    "volume": 576721.0
  },
  {
    "time": 1455116400,
    "open": 77800.0,
    "high": 79500.0,
    "low": 65700.0,
    "close": 68000.0,
    "volume": 432732.0
  },
  {
    "time": 1455462000,
    "open": 68100.0,
    "high": 73300.0,
    "low": 66500.0,
    "close": 72400.0,
    "volume": 468500.0
  },
  {
    "time": 1456066800,
    "open": 71800.0,
    "high": 73000.0,
    "low": 69300.0,
    "close": 71600.0,
    "volume": 418655.0
  },
  {
    "time": 1456671600,
    "open": 72500.0,
    "high": 75400.0,
    "low": 70400.0,
    "close": 75300.0,
    "volume": 383260.0
  },
  {
    "time": 1457276400,
    "open": 75500.0,
    "high": 76800.0,
    "low": 72200.0,
    "close": 72400.0,
    "volume": 607285.0
  },
  {
    "time": 1457881200,
    "open": 72200.0,
    "high": 72400.0,
    "low": 69600.0,
    "close": 70600.0,
    "volume": 314686.0
  },
  {
    "time": 1458486000,
    "open": 70900.0,
    "high": 71800.0,
    "low": 66900.0,
    "close": 67100.0,
    "volume": 329136.0
  },
  {
    "time": 1459090800,
    "open": 67600.0,
    "high": 68600.0,
    "low": 65400.0,
    "close": 67200.0,
    "volume": 246098.0
  },
  {
    "time": 1459695600,
    "open": 68000.0,
    "high": 68800.0,
    "low": 65100.0,
    "close": 66000.0,
    "volume": 259778.0
  },
  {
    "time": 1460300400,
    "open": 66300.0,
    "high": 66800.0,
    "low": 62000.0,
    "close": 62700.0,
    "volume": 219390.0
  },
  {
    "time": 1460905200,
    "open": 62100.0,
    "high": 66300.0,
    "low": 62100.0,
    "close": 63500.0,
    "volume": 205779.0
  },
  {
    "time": 1461510000,
    "open": 64300.0,
    "high": 64700.0,
    "low": 61200.0,
    "close": 61400.0,
    "volume": 213632.0
  },
  {
    "time": 1462114800,
    "open": 61300.0,
    "high": 61400.0,
    "low": 58900.0,
    "close": 60300.0,
    "volume": 164316.0
  },
  {
    "time": 1462719600,
    "open": 60300.0,
    "high": 61400.0,
    "low": 58200.0,
    "close": 59800.0,
    "volume": 301410.0
  },
  {
    "time": 1463324400,
    "open": 60500.0,
    "high": 60600.0,
    "low": 53600.0,
    "close": 55000.0,
    "volume": 318552.0
  },
  {
    "time": 1463929200,
    "open": 54900.0,
    "high": 57300.0,
    "low": 54200.0,
    "close": 55300.0,
    "volume": 205137.0
  },
  {
    "time": 1464534000,
    "open": 55400.0,
    "high": 58000.0,
    "low": 53500.0,
    "close": 56500.0,
    "volume": 227082.0
  },
  {
    "time": 1465225200,
    "open": 57100.0,
    "high": 59400.0,
    "low": 55800.0,
    "close": 58900.0,
    "volume": 274458.0
  },
  {
    "time": 1465743600,
    "open": 58100.0,
    "high": 58800.0,
    "low": 56100.0,
    "close": 56500.0,
    "volume": 268745.0
  },
  {
    "time": 1466348400,
    "open": 56000.0,
    "high": 59400.0,
    "low": 50400.0,
    "close": 50800.0,
    "volume": 411090.0
  },
  {
    "time": 1466953200,
    "open": 48600.0,
    "high": 53500.0,
    "low": 48600.0,
    "close": 53100.0,
    "volume": 249096.0
  },
  {
    "time": 1467558000,
    "open": 53200.0,
    "high": 56500.0,
    "low": 51900.0,
    "close": 53900.0,
    "volume": 366960.0
  },
  {
    "time": 1468162800,
    "open": 53900.0,
    "high": 55400.0,
    "low": 53400.0,
    "close": 54000.0,
    "volume": 211769.0
  },
  {
    "time": 1468767600,
    "open": 54000.0,
    "high": 54600.0,
    "low": 52500.0,
    "close": 53800.0,
    "volume": 140707.0
  },
  {
    "time": 1469372400,
    "open": 53800.0,
    "high": 56500.0,
    "low": 53100.0,
    "close": 55600.0,
    "volume": 271903.0
  },
  {
    "time": 1469977200,
    "open": 56000.0,
    "high": 56000.0,
    "low": 51400.0,
    "close": 51800.0,
    "volume": 209009.0
  },
  {
    "time": 1470582000,
    "open": 51500.0,
    "high": 54100.0,
    "low": 51300.0,
    "close": 54100.0,
    "volume": 181142.0
  },
  {
    "time": 1471273200,
    "open": 54900.0,
    "high": 56400.0,
    "low": 54400.0,
    "close": 54500.0,
    "volume": 307218.0
  },
  {
    "time": 1471791600,
    "open": 54800.0,
    "high": 54800.0,
    "low": 52100.0,
    "close": 52300.0,
    "volume": 168153.0
  },
  {
    "time": 1472396400,
    "open": 52300.0,
    "high": 52500.0,
    "low": 49300.0,
    "close": 51500.0,
    "volume": 211720.0
  },
  {
    "time": 1473001200,
    "open": 52000.0,
    "high": 52300.0,
    "low": 51000.0,
    "close": 51500.0,
    "volume": 145409.0
  },
  {
    "time": 1473606000,
    "open": 50400.0,
    "high": 50900.0,
    "low": 49900.0,
    "close": 50400.0,
    "volume": 40497.0
  },
  {
    "time": 1474210800,
    "open": 50500.0,
    "high": 51700.0,
    "low": 49700.0,
    "close": 51500.0,
    "volume": 128094.0
  },
  {
    "time": 1474815600,
    "open": 51500.0,
    "high": 51800.0,
    "low": 49200.0,
    "close": 49250.0,
    "volume": 169961.0
  },
  {
    "time": 1475506800,
    "open": 49200.0,
    "high": 49350.0,
    "low": 46850.0,
    "close": 46900.0,
    "volume": 174238.0
  },
  {
    "time": 1476025200,
    "open": 46900.0,
    "high": 46950.0,
    "low": 43950.0,
    "close": 45100.0,
    "volume": 261139.0
  },
  {
    "time": 1476630000,
    "open": 45300.0,
    "high": 45400.0,
    "low": 43000.0,
    "close": 43050.0,
    "volume": 110969.0
  },
  {
    "time": 1477234800,
    "open": 43100.0,
    "high": 45000.0,
    "low": 40500.0,
    "close": 44400.0,
    "volume": 199242.0
  },
  {
    "time": 1477839600,
    "open": 44400.0,
    "high": 44500.0,
    "low": 42000.0,
    "close": 43850.0,
    "volume": 177263.0
  },
  {
    "time": 1478444400,
    "open": 44900.0,
    "high": 46100.0,
    "low": 40050.0,
    "close": 44850.0,
    "volume": 331765.0
  },
  {
    "time": 1479049200,
    "open": 45000.0,
    "high": 45750.0,
    "low": 43150.0,
    "close": 43550.0,
    "volume": 118781.0
  },
  {
    "time": 1479654000,
    "open": 43300.0,
    "high": 43650.0,
    "low": 39150.0,
    "close": 40000.0,
    "volume": 211592.0
  },
  {
    "time": 1480258800,
    "open": 39900.0,
    "high": 41600.0,
    "low": 39450.0,
    "close": 41100.0,
    "volume": 102415.0
  },
  {
    "time": 1480863600,
    "open": 40450.0,
    "high": 42200.0,
    "low": 40000.0,
    "close": 41450.0,
    "volume": 109260.0
  },
  {
    "time": 1481468400,
    "open": 41900.0,
    "high": 43500.0,
    "low": 41600.0,
    "close": 43250.0,
    "volume": 141296.0
  },
  {
    "time": 1482073200,
    "open": 43250.0,
    "high": 43300.0,
    "low": 39500.0,
    "close": 39950.0,
    "volume": 470153.0
  },
  {
    "time": 1482678000,
    "open": 40000.0,
    "high": 40700.0,
    "low": 39500.0,
    "close": 40400.0,
    "volume": 124336.0
  },
  {
    "time": 1483282800,
    "open": 40450.0,
    "high": 42500.0,
    "low": 39650.0,
    "close": 41800.0,
    "volume": 159530.0
  },
  {
    "time": 1483887600,
    "open": 42050.0,
    "high": 42200.0,
    "low": 39000.0,
    "close": 39550.0,
    "volume": 200310.0
  },
  {
    "time": 1484492400,
    "open": 39450.0,
    "high": 39900.0,
    "low": 38150.0,
    "close": 38250.0,
    "volume": 128604.0
  },
  {
    "time": 1485097200,
    "open": 38350.0,
    "high": 38350.0,
    "low": 35050.0,
    "close": 35450.0,
    "volume": 172140.0
  },
  {
    "time": 1485788400,
    "open": 35700.0,
    "high": 36700.0,
    "low": 35150.0,
    "close": 35300.0,
    "volume": 68465.0
  },
  {
    "time": 1486306800,
    "open": 35200.0,
    "high": 36650.0,
    "low": 35150.0,
    "close": 35800.0,
    "volume": 77429.0
  },
  {
    "time": 1486911600,
    "open": 36000.0,
    "high": 38500.0,
    "low": 35800.0,
    "close": 37700.0,
    "volume": 119122.0
  },
  {
    "time": 1487516400,
    "open": 37950.0,
    "high": 37950.0,
    "low": 36550.0,
    "close": 36800.0,
    "volume": 76395.0
  },
  {
    "time": 1488121200,
    "open": 36850.0,
    "high": 37950.0,
    "low": 35300.0,
    "close": 35550.0,
    "volume": 110524.0
  },
  {
    "time": 1488726000,
    "open": 35400.0,
    "high": 35850.0,
    "low": 33200.0,
    "close": 34150.0,
    "volume": 114779.0
  },
  {
    "time": 1489330800,
    "open": 34100.0,
    "high": 34750.0,
    "low": 32450.0,
    "close": 33150.0,
    "volume": 140364.0
  },
  {
    "time": 1489935600,
    "open": 33150.0,
    "high": 33600.0,
    "low": 32000.0,
    "close": 32800.0,
    "volume": 118445.0
  },
  {
    "time": 1490540400,
    "open": 33400.0,
    "high": 33550.0,
    "low": 31750.0,
    "close": 32550.0,
    "volume": 125009.0
  },
  {
    "time": 1491145200,
    "open": 32900.0,
    "high": 34400.0,
    "low": 32600.0,
    "close": 33800.0,
    "volume": 137104.0
  },
  {
    "time": 1491750000,
    "open": 33800.0,
    "high": 34350.0,
    "low": 32500.0,
    "close": 33850.0,
    "volume": 109834.0
  },
  {
    "time": 1492354800,
    "open": 33900.0,
    "high": 37100.0,
    "low": 33800.0,
    "close": 36100.0,
    "volume": 278486.0
  },
  {
    "time": 1492959600,
    "open": 36100.0,
    "high": 36600.0,
    "low": 35000.0,
    "close": 35750.0,
    "volume": 118505.0
  },
  {
    "time": 1493650800,
    "open": 35300.0,
    "high": 35600.0,
    "low": 34500.0,
    "close": 35250.0,
    "volume": 36559.0
  },
  {
    "time": 1494169200,
    "open": 35550.0,
    "high": 37000.0,
    "low": 35300.0,
    "close": 35800.0,
    "volume": 99867.0
  },
  {
    "time": 1494774000,
    "open": 35850.0,
    "high": 36400.0,
    "low": 34200.0,
    "close": 35800.0,
    "volume": 101368.0
  },
  {
    "time": 1495378800,
    "open": 35700.0,
    "high": 40800.0,
    "low": 35400.0,
    "close": 40650.0,
    "volume": 560278.0
  },
  {
    "time": 1495983600,
    "open": 41000.0,
    "high": 41500.0,
    "low": 39800.0,
    "close": 40350.0,
    "volume": 238446.0
  },
  {
    "time": 1496588400,
    "open": 40600.0,
    "high": 41150.0,
    "low": 39900.0,
    "close": 40950.0,
    "volume": 168867.0
  },
  {
    "time": 1497193200,
    "open": 41650.0,
    "high": 43650.0,
    "low": 41350.0,
    "close": 41450.0,
    "volume": 422280.0
  },
  {
    "time": 1497798000,
    "open": 41400.0,
    "high": 42300.0,
    "low": 39950.0,
    "close": 39950.0,
    "volume": 151321.0
  },
  {
    "time": 1498402800,
    "open": 40550.0,
    "high": 40600.0,
    "low": 37950.0,
    "close": 39200.0,
    "volume": 177218.0
  },
  {
    "time": 1499007600,
    "open": 38800.0,
    "high": 40650.0,
    "low": 38000.0,
    "close": 38650.0,
    "volume": 145574.0
  },
  {
    "time": 1499612400,
    "open": 38800.0,
    "high": 38800.0,
    "low": 35950.0,
    "close": 36700.0,
    "volume": 136664.0
  },
  {
    "time": 1500217200,
    "open": 36600.0,
    "high": 38350.0,
    "low": 36600.0,
    "close": 38100.0,
    "volume": 116511.0
  },
  {
    "time": 1500822000,
    "open": 38200.0,
    "high": 39150.0,
    "low": 36800.0,
    "close": 38050.0,
    "volume": 162138.0
  },
  {
    "time": 1501426800,
    "open": 37800.0,
    "high": 38300.0,
    "low": 36500.0,
    "close": 37700.0,
    "volume": 134657.0
  },
  {
    "time": 1502031600,
    "open": 37650.0,
    "high": 43200.0,
    "low": 37450.0,
    "close": 42000.0,
    "volume": 490394.0
  },
  {
    "time": 1502636400,
    "open": 42200.0,
    "high": 42950.0,
    "low": 40350.0,
    "close": 40650.0,
    "volume": 352192.0
  },
  {
    "time": 1503241200,
    "open": 40750.0,
    "high": 43250.0,
    "low": 39400.0,
    "close": 43050.0,
    "volume": 495565.0
  },
  {
    "time": 1503846000,
    "open": 43100.0,
    "high": 48900.0,
    "low": 42800.0,
    "close": 48900.0,
    "volume": 790387.0
  },
  {
    "time": 1504450800,
    "open": 47050.0,
    "high": 49400.0,
    "low": 44000.0,
    "close": 44250.0,
    "volume": 832594.0
  },
  {
    "time": 1505055600,
    "open": 44100.0,
    "high": 45150.0,
    "low": 40750.0,
    "close": 41000.0,
    "volume": 592323.0
  },
  {
    "time": 1505660400,
    "open": 41300.0,
    "high": 42600.0,
    "low": 37450.0,
    "close": 38200.0,
    "volume": 490567.0
  },
  {
    "time": 1506265200,
    "open": 38600.0,
    "high": 39850.0,
    "low": 37050.0,
    "close": 39750.0,
    "volume": 286725.0
  },
  {
    "time": 1507561200,
    "open": 40400.0,
    "high": 42250.0,
    "low": 39500.0,
    "close": 41750.0,
    "volume": 261939.0
  },
  {
    "time": 1508079600,
    "open": 42350.0,
    "high": 43300.0,
    "low": 40550.0,
    "close": 41850.0,
    "volume": 319816.0
  },
  {
    "time": 1508684400,
    "open": 42200.0,
    "high": 47000.0,
    "low": 41300.0,
    "close": 46600.0,
    "volume": 426544.0
  },
  {
    "time": 1509289200,
    "open": 47000.0,
    "high": 47300.0,
    "low": 43900.0,
    "close": 45650.0,
    "volume": 405783.0
  },
  {
    "time": 1509894000,
    "open": 46000.0,
    "high": 47500.0,
    "low": 44700.0,
    "close": 45000.0,
    "volume": 395119.0
  },
  {
    "time": 1510498800,
    "open": 45000.0,
    "high": 54800.0,
    "low": 44500.0,
    "close": 53600.0,
    "volume": 1176979.0
  },
  {
    "time": 1511103600,
    "open": 53600.0,
    "high": 55800.0,
    "low": 48500.0,
    "close": 53300.0,
    "volume": 859954.0
  },
  {
    "time": 1511708400,
    "open": 53000.0,
    "high": 60500.0,
    "low": 53000.0,
    "close": 57600.0,
    "volume": 1327985.0
  },
  {
    "time": 1512313200,
    "open": 57600.0,
    "high": 59100.0,
    "low": 47600.0,
    "close": 48700.0,
    "volume": 851871.0
  },
  {
    "time": 1512918000,
    "open": 51700.0,
    "high": 59100.0,
    "low": 50600.0,
    "close": 58000.0,
    "volume": 1083302.0
  },
  {
    "time": 1513522800,
    "open": 57800.0,
    "high": 59300.0,
    "low": 54600.0,
    "close": 59100.0,
    "volume": 529014.0
  },
  {
    "time": 1514214000,
    "open": 60500.0,
    "high": 61300.0,
    "low": 57100.0,
    "close": 58900.0,
    "volume": 353675.0
  },
  {
    "time": 1514818800,
    "open": 60000.0,
    "high": 65800.0,
    "low": 58800.0,
    "close": 63300.0,
    "volume": 716421.0
  },
  {
    "time": 1515337200,
    "open": 64100.0,
    "high": 71200.0,
    "low": 62200.0,
    "close": 68400.0,
    "volume": 868930.0
  },
  {
    "time": 1515942000,
    "open": 68300.0,
    "high": 69100.0,
    "low": 64900.0,
    "close": 66300.0,
    "volume": 566875.0
  },
  {
    "time": 1516546800,
    "open": 66100.0,
    "high": 67900.0,
    "low": 65100.0,
    "close": 67800.0,
    "volume": 390685.0
  },
  {
    "time": 1517151600,
    "open": 68700.0,
    "high": 68800.0,
    "low": 60100.0,
    "close": 61000.0,
    "volume": 646906.0
  },
  {
    "time": 1517756400,
    "open": 59300.0,
    "high": 60000.0,
    "low": 53200.0,
    "close": 58000.0,
    "volume": 557925.0
  },
  {
    "time": 1518361200,
    "open": 57800.0,
    "high": 60100.0,
    "low": 56500.0,
    "close": 58500.0,
    "volume": 145042.0
  },
  {
    "time": 1518966000,
    "open": 59100.0,
    "high": 62000.0,
    "low": 58900.0,
    "close": 61400.0,
    "volume": 214484.0
  },
  {
    "time": 1519570800,
    "open": 62500.0,
    "high": 63900.0,
    "low": 57400.0,
    "close": 59200.0,
    "volume": 194911.0
  },
  {
    "time": 1520175600,
    "open": 59500.0,
    "high": 60600.0,
    "low": 57900.0,
    "close": 60600.0,
    "volume": 147918.0
  },
  {
    "time": 1520780400,
    "open": 59900.0,
    "high": 63800.0,
    "low": 56300.0,
    "close": 56900.0,
    "volume": 450131.0
  },
  {
    "time": 1521385200,
    "open": 56700.0,
    "high": 58200.0,
    "low": 51600.0,
    "close": 51700.0,
    "volume": 298678.0
  },
  {
    "time": 1521990000,
    "open": 50700.0,
    "high": 55000.0,
    "low": 50700.0,
    "close": 54400.0,
    "volume": 177800.0
  },
  {
    "time": 1522594800,
    "open": 54800.0,
    "high": 56100.0,
    "low": 52600.0,
    "close": 52600.0,
    "volume": 220416.0
  },
  {
    "time": 1523199600,
    "open": 52300.0,
    "high": 56600.0,
    "low": 52300.0,
    "close": 54100.0,
    "volume": 218356.0
  },
  {
    "time": 1523804400,
    "open": 54100.0,
    "high": 57000.0,
    "low": 50800.0,
    "close": 50800.0,
    "volume": 338419.0
  },
  {
    "time": 1524409200,
    "open": 50500.0,
    "high": 51300.0,
    "low": 46900.0,
    "close": 48650.0,
    "volume": 306335.0
  },
  {
    "time": 1525014000,
    "open": 48150.0,
    "high": 49700.0,
    "low": 45450.0,
    "close": 45550.0,
    "volume": 213862.0
  },
  {
    "time": 1525705200,
    "open": 45650.0,
    "high": 47100.0,
    "low": 42800.0,
    "close": 45950.0,
    "volume": 167789.0
  },
  {
    "time": 1526223600,
    "open": 45950.0,
    "high": 45950.0,
    "low": 42300.0,
    "close": 43400.0,
    "volume": 167163.0
  },
  {
    "time": 1526828400,
    "open": 43450.0,
    "high": 44100.0,
    "low": 42400.0,
    "close": 43050.0,
    "volume": 93325.0
  },
  {
    "time": 1527433200,
    "open": 43000.0,
    "high": 44700.0,
    "low": 40300.0,
    "close": 43950.0,
    "volume": 170115.0
  },
  {
    "time": 1528038000,
    "open": 43950.0,
    "high": 43950.0,
    "low": 42000.0,
    "close": 42050.0,
    "volume": 101675.0
  },
  {
    "time": 1528642800,
    "open": 42000.0,
    "high": 43850.0,
    "low": 41050.0,
    "close": 41200.0,
    "volume": 133390.0
  },
  {
    "time": 1529247600,
    "open": 41400.0,
    "high": 41450.0,
    "low": 37500.0,
    "close": 38600.0,
    "volume": 163874.0
  },
  {
    "time": 1529852400,
    "open": 38700.0,
    "high": 40800.0,
    "low": 37200.0,
    "close": 38450.0,
    "volume": 154161.0
  },
  {
    "time": 1530457200,
    "open": 38400.0,
    "high": 43500.0,
    "low": 36150.0,
    "close": 41700.0,
    "volume": 409778.0
  },
  {
    "time": 1531062000,
    "open": 41650.0,
    "high": 42350.0,
    "low": 40100.0,
    "close": 42050.0,
    "volume": 191339.0
  },
  {
    "time": 1531666800,
    "open": 42950.0,
    "high": 43900.0,
    "low": 40600.0,
    "close": 41100.0,
    "volume": 164354.0
  },
  {
    "time": 1532271600,
    "open": 41300.0,
    "high": 41700.0,
    "low": 37950.0,
    "close": 39000.0,
    "volume": 159033.0
  },
  {
    "time": 1532876400,
    "open": 39250.0,
    "high": 40150.0,
    "low": 37650.0,
    "close": 39400.0,
    "volume": 96483.0
  },
  {
    "time": 1533481200,
    "open": 39400.0,
    "high": 41600.0,
    "low": 38800.0,
    "close": 40850.0,
    "volume": 125627.0
  },
  {
    "time": 1534086000,
    "open": 40850.0,
    "high": 41750.0,
    "low": 38550.0,
    "close": 41500.0,
    "volume": 131899.0
  },
  {
    "time": 1534690800,
    "open": 41750.0,
    "high": 42950.0,
    "low": 41250.0,
    "close": 42900.0,
    "volume": 132314.0
  },
  {
    "time": 1535295600,
    "open": 43100.0,
    "high": 43500.0,
    "low": 41850.0,
    "close": 43100.0,
    "volume": 105888.0
  },
  {
    "time": 1535900400,
    "open": 43500.0,
    "high": 43750.0,
    "low": 41000.0,
    "close": 41850.0,
    "volume": 152268.0
  },
  {
    "time": 1536505200,
    "open": 41500.0,
    "high": 42950.0,
    "low": 41400.0,
    "close": 42150.0,
    "volume": 113837.0
  },
  {
    "time": 1537110000,
    "open": 41900.0,
    "high": 45900.0,
    "low": 41300.0,
    "close": 45200.0,
    "volume": 265697.0
  },
  {
    "time": 1537974000,
    "open": 45200.0,
    "high": 45900.0,
    "low": 44550.0,
    "close": 44850.0,
    "volume": 72545.0
  },
  {
    "time": 1538319600,
    "open": 44850.0,
    "high": 44850.0,
    "low": 39850.0,
    "close": 40000.0,
    "volume": 151950.0
  },
  {
    "time": 1538924400,
    "open": 39400.0,
    "high": 40350.0,
    "low": 35100.0,
    "close": 36500.0,
    "volume": 188439.0
  },
  {
    "time": 1539529200,
    "open": 36100.0,
    "high": 36900.0,
    "low": 34500.0,
    "close": 36500.0,
    "volume": 136055.0
  },
  {
    "time": 1540134000,
    "open": 36300.0,
    "high": 39200.0,
    "low": 34150.0,
    "close": 34150.0,
    "volume": 161737.0
  },
  {
    "time": 1540738800,
    "open": 34550.0,
    "high": 35200.0,
    "low": 31950.0,
    "close": 34600.0,
    "volume": 169590.0
  },
  {
    "time": 1541343600,
    "open": 34350.0,
    "high": 34600.0,
    "low": 33450.0,
    "close": 34000.0,
    "volume": 123557.0
  },
  {
    "time": 1541948400,
    "open": 34050.0,
    "high": 34800.0,
    "low": 32100.0,
    "close": 34700.0,
    "volume": 116371.0
  },
  {
    "time": 1542553200,
    "open": 34300.0,
    "high": 35350.0,
    "low": 33100.0,
    "close": 33250.0,
    "volume": 103863.0
  },
  {
    "time": 1543158000,
    "open": 33200.0,
    "high": 34950.0,
    "low": 33200.0,
    "close": 33250.0,
    "volume": 71289.0
  },
  {
    "time": 1543762800,
    "open": 33800.0,
    "high": 34800.0,
    "low": 32850.0,
    "close": 33300.0,
    "volume": 82891.0
  },
  {
    "time": 1544367600,
    "open": 32900.0,
    "high": 34250.0,
    "low": 31500.0,
    "close": 33600.0,
    "volume": 117783.0
  },
  {
    "time": 1544972400,
    "open": 33050.0,
    "high": 34100.0,
    "low": 31750.0,
    "close": 32000.0,
    "volume": 81391.0
  },
  {
    "time": 1545577200,
    "open": 31850.0,
    "high": 34000.0,
    "low": 31750.0,
    "close": 33650.0,
    "volume": 83448.0
  },
  {
    "time": 1546354800,
    "open": 33700.0,
    "high": 34050.0,
    "low": 31000.0,
    "close": 31550.0,
    "volume": 73917.0
  },
  {
    "time": 1546786800,
    "open": 31600.0,
    "high": 33500.0,
    "low": 31600.0,
    "close": 32600.0,
    "volume": 93176.0
  },
  {
    "time": 1547391600,
    "open": 32800.0,
    "high": 33600.0,
    "low": 32050.0,
    "close": 32900.0,
    "volume": 88026.0
  },
  {
    "time": 1547996400,
    "open": 32900.0,
    "high": 34200.0,
    "low": 32550.0,
    "close": 34000.0,
    "volume": 82334.0
  },
  {
    "time": 1548601200,
    "open": 33950.0,
    "high": 34450.0,
    "low": 32900.0,
    "close": 33400.0,
    "volume": 105139.0
  },
  {
    "time": 1549465200,
    "open": 33300.0,
    "high": 33600.0,
    "low": 32700.0,
    "close": 32750.0,
    "volume": 40846.0
  },
  {
    "time": 1549810800,
    "open": 32750.0,
    "high": 35400.0,
    "low": 31500.0,
    "close": 34700.0,
    "volume": 191194.0
  },
  {
    "time": 1550415600,
    "open": 35600.0,
    "high": 40750.0,
    "low": 35100.0,
    "close": 39150.0,
    "volume": 778866.0
  },
  {
    "time": 1551020400,
    "open": 39000.0,
    "high": 40800.0,
    "low": 37850.0,
    "close": 38750.0,
    "volume": 248153.0
  },
  {
    "time": 1551625200,
    "open": 39300.0,
    "high": 40500.0,
    "low": 38050.0,
    "close": 38200.0,
    "volume": 183259.0
  },
  {
    "time": 1552230000,
    "open": 38200.0,
    "high": 40500.0,
    "low": 37250.0,
    "close": 38500.0,
    "volume": 200766.0
  },
  {
    "time": 1552834800,
    "open": 38550.0,
    "high": 39300.0,
    "low": 37050.0,
    "close": 37900.0,
    "volume": 137049.0
  },
  {
    "time": 1553439600,
    "open": 37750.0,
    "high": 38250.0,
    "low": 36100.0,
    "close": 38000.0,
    "volume": 89012.0
  },
  {
    "time": 1554044400,
    "open": 38250.0,
    "high": 43500.0,
    "low": 37800.0,
    "close": 41650.0,
    "volume": 338834.0
  },
  {
    "time": 1554649200,
    "open": 41850.0,
    "high": 44000.0,
    "low": 41100.0,
    "close": 41550.0,
    "volume": 230181.0
  },
  {
    "time": 1555254000,
    "open": 41250.0,
    "high": 42850.0,
    "low": 40400.0,
    "close": 42800.0,
    "volume": 148130.0
  },
  {
    "time": 1555858800,
    "open": 42600.0,
    "high": 42750.0,
    "low": 40300.0,
    "close": 40750.0,
    "volume": 137000.0
  },
  {
    "time": 1556463600,
    "open": 41700.0,
    "high": 41900.0,
    "low": 40250.0,
    "close": 41450.0,
    "volume": 75461.0
  },
  {
    "time": 1557154800,
    "open": 40950.0,
    "high": 41550.0,
    "low": 38450.0,
    "close": 39400.0,
    "volume": 97963.0
  },
  {
    "time": 1557673200,
    "open": 39400.0,
    "high": 45300.0,
    "low": 37000.0,
    "close": 44150.0,
    "volume": 359109.0
  },
  {
    "time": 1558278000,
    "open": 45150.0,
    "high": 46500.0,
    "low": 43850.0,
    "close": 44450.0,
    "volume": 458241.0
  },
  {
    "time": 1558882800,
    "open": 45050.0,
    "high": 51100.0,
    "low": 44450.0,
    "close": 49500.0,
    "volume": 616740.0
  },
  {
    "time": 1559487600,
    "open": 49050.0,
    "high": 50700.0,
    "low": 47600.0,
    "close": 48750.0,
    "volume": 236997.0
  },
  {
    "time": 1560092400,
    "open": 48750.0,
    "high": 52100.0,
    "low": 48100.0,
    "close": 48550.0,
    "volume": 297557.0
  },
  {
    "time": 1560697200,
    "open": 48400.0,
    "high": 48800.0,
    "low": 43500.0,
    "close": 45800.0,
    "volume": 304783.0
  },
  {
    "time": 1561302000,
    "open": 46000.0,
    "high": 46150.0,
    "low": 41700.0,
    "close": 41900.0,
    "volume": 212312.0
  },
  {
    "time": 1561906800,
    "open": 42800.0,
    "high": 44050.0,
    "low": 41500.0,
    "close": 42200.0,
    "volume": 161707.0
  },
  {
    "time": 1562511600,
    "open": 42350.0,
    "high": 42350.0,
    "low": 39650.0,
    "close": 41150.0,
    "volume": 167973.0
  },
  {
    "time": 1563116400,
    "open": 40800.0,
    "high": 42000.0,
    "low": 39150.0,
    "close": 39800.0,
    "volume": 145879.0
  },
  {
    "time": 1563721200,
    "open": 39450.0,
    "high": 39900.0,
    "low": 36500.0,
    "close": 37200.0,
    "volume": 163441.0
  },
  {
    "time": 1564326000,
    "open": 37150.0,
    "high": 37500.0,
    "low": 34350.0,
    "close": 35050.0,
    "volume": 148581.0
  },
  {
    "time": 1564930800,
    "open": 34600.0,
    "high": 35500.0,
    "low": 30850.0,
    "close": 34950.0,
    "volume": 259359.0
  },
  {
    "time": 1565535600,
    "open": 34950.0,
    "high": 35850.0,
    "low": 34200.0,
    "close": 34600.0,
    "volume": 111902.0
  },
  {
    "time": 1566140400,
    "open": 34850.0,
    "high": 36650.0,
    "low": 33100.0,
    "close": 33950.0,
    "volume": 244793.0
  },
  {
    "time": 1566745200,
    "open": 32900.0,
    "high": 34800.0,
    "low": 31350.0,
    "close": 34550.0,
    "volume": 224201.0
  },
  {
    "time": 1567350000,
    "open": 34100.0,
    "high": 35150.0,
    "low": 33400.0,
    "close": 33800.0,
    "volume": 120150.0
  },
  {
    "time": 1567954800,
    "open": 33800.0,
    "high": 34700.0,
    "low": 33250.0,
    "close": 34250.0,
    "volume": 70440.0
  },
  {
    "time": 1568559600,
    "open": 34700.0,
    "high": 35400.0,
    "low": 34000.0,
    "close": 34300.0,
    "volume": 132463.0
  },
  {
    "time": 1569164400,
    "open": 34000.0,
    "high": 34650.0,
    "low": 32450.0,
    "close": 32700.0,
    "volume": 139424.0
  },
  {
    "time": 1569769200,
    "open": 32650.0,
    "high": 33200.0,
    "low": 31800.0,
    "close": 32300.0,
    "volume": 105582.0
  },
  {
    "time": 1570374000,
    "open": 32700.0,
    "high": 33800.0,
    "low": 31850.0,
    "close": 33050.0,
    "volume": 127001.0
  },
  {
    "time": 1570978800,
    "open": 33300.0,
    "high": 36000.0,
    "low": 33000.0,
    "close": 34100.0,
    "volume": 161349.0
  },
  {
    "time": 1571583600,
    "open": 34100.0,
    "high": 35000.0,
    "low": 33250.0,
    "close": 33950.0,
    "volume": 120852.0
  },
  {
    "time": 1572188400,
    "open": 33950.0,
    "high": 35400.0,
    "low": 33050.0,
    "close": 33950.0,
    "volume": 166497.0
  },
  {
    "time": 1572793200,
    "open": 33950.0,
    "high": 36800.0,
    "low": 33950.0,
    "close": 35200.0,
    "volume": 206555.0
  },
  {
    "time": 1573398000,
    "open": 35100.0,
    "high": 35800.0,
    "low": 34200.0,
    "close": 35300.0,
    "volume": 106566.0
  },
  {
    "time": 1574002800,
    "open": 35150.0,
    "high": 35500.0,
    "low": 32350.0,
    "close": 32700.0,
    "volume": 141978.0
  },
  {
    "time": 1574607600,
    "open": 32700.0,
    "high": 34900.0,
    "low": 32700.0,
    "close": 33700.0,
    "volume": 91503.0
  },
  {
    "time": 1575212400,
    "open": 34000.0,
    "high": 35700.0,
    "low": 32750.0,
    "close": 35650.0,
    "volume": 136431.0
  },
  {
    "time": 1575817200,
    "open": 35950.0,
    "high": 37200.0,
    "low": 34200.0,
    "close": 36500.0,
    "volume": 171959.0
  },
  {
    "time": 1576422000,
    "open": 36400.0,
    "high": 36400.0,
    "low": 34400.0,
    "close": 34550.0,
    "volume": 113151.0
  },
  {
    "time": 1577026800,
    "open": 34850.0,
    "high": 36000.0,
    "low": 34100.0,
    "close": 35850.0,
    "volume": 106869.0
  },
  {
    "time": 1577631600,
    "open": 36000.0,
    "high": 36600.0,
    "low": 35200.0,
    "close": 35200.0,
    "volume": 85318.0
  },
  {
    "time": 1578236400,
    "open": 35000.0,
    "high": 35700.0,
    "low": 32800.0,
    "close": 35400.0,
    "volume": 178697.0
  },
  {
    "time": 1578841200,
    "open": 36200.0,
    "high": 40100.0,
    "low": 36200.0,
    "close": 39400.0,
    "volume": 411149.0
  },
  {
    "time": 1579446000,
    "open": 39750.0,
    "high": 41200.0,
    "low": 38100.0,
    "close": 40300.0,
    "volume": 192657.0
  },
  {
    "time": 1580137200,
    "open": 37400.0,
    "high": 39700.0,
    "low": 37350.0,
    "close": 38850.0,
    "volume": 231301.0
  },
  {
    "time": 1580655600,
    "open": 37800.0,
    "high": 41200.0,
    "low": 37750.0,
    "close": 39100.0,
    "volume": 223068.0
  },
  {
    "time": 1581260400,
    "open": 39300.0,
    "high": 40350.0,
    "low": 37950.0,
    "close": 39700.0,
    "volume": 190599.0
  },
  {
    "time": 1581865200,
    "open": 39800.0,
    "high": 47650.0,
    "low": 38700.0,
    "close": 44950.0,
    "volume": 1367564.0
  },
  {
    "time": 1582470000,
    "open": 43600.0,
    "high": 46100.0,
    "low": 39600.0,
    "close": 40650.0,
    "volume": 775577.0
  },
  {
    "time": 1583074800,
    "open": 41100.0,
    "high": 49500.0,
    "low": 40100.0,
    "close": 45400.0,
    "volume": 1086560.0
  },
  {
    "time": 1583679600,
    "open": 44500.0,
    "high": 45700.0,
    "low": 32550.0,
    "close": 35250.0,
    "volume": 975799.0
  },
  {
    "time": 1584284400,
    "open": 35900.0,
    "high": 36850.0,
    "low": 30350.0,
    "close": 33400.0,
    "volume": 1058123.0
  },
  {
    "time": 1584889200,
    "open": 30600.0,
    "high": 37300.0,
    "low": 29700.0,
    "close": 34600.0,
    "volume": 824759.0
  },
  {
    "time": 1585494000,
    "open": 33800.0,
    "high": 40050.0,
    "low": 33050.0,
    "close": 39500.0,
    "volume": 557398.0
  },
  {
    "time": 1586098800,
    "open": 39500.0,
    "high": 41900.0,
    "low": 37400.0,
    "close": 39050.0,
    "volume": 452171.0
  },
  {
    "time": 1586703600,
    "open": 38500.0,
    "high": 41000.0,
    "low": 37550.0,
    "close": 40100.0,
    "volume": 327598.0
  },
  {
    "time": 1587308400,
    "open": 42000.0,
    "high": 43150.0,
    "low": 38350.0,
    "close": 39600.0,
    "volume": 563738.0
  },
  {
    "time": 1587913200,
    "open": 40050.0,
    "high": 43050.0,
    "low": 39650.0,
    "close": 42600.0,
    "volume": 316130.0
  },
  {
    "time": 1588518000,
    "open": 42000.0,
    "high": 47350.0,
    "low": 41050.0,
    "close": 45400.0,
    "volume": 592527.0
  },
  {
    "time": 1589122800,
    "open": 45400.0,
    "high": 52000.0,
    "low": 44800.0,
    "close": 50500.0,
    "volume": 1061816.0
  },
  {
    "time": 1589727600,
    "open": 50900.0,
    "high": 55600.0,
    "low": 49600.0,
    "close": 53500.0,
    "volume": 803217.0
  },
  {
    "time": 1590332400,
    "open": 53900.0,
    "high": 54600.0,
    "low": 49000.0,
    "close": 52600.0,
    "volume": 727748.0
  },
  {
    "time": 1590937200,
    "open": 52500.0,
    "high": 58500.0,
    "low": 51400.0,
    "close": 55300.0,
    "volume": 821819.0
  },
  {
    "time": 1591542000,
    "open": 55800.0,
    "high": 62000.0,
    "low": 55700.0,
    "close": 59500.0,
    "volume": 1132172.0
  },
  {
    "time": 1592146800,
    "open": 59400.0,
    "high": 61000.0,
    "low": 53500.0,
    "close": 59600.0,
    "volume": 777148.0
  },
  {
    "time": 1592751600,
    "open": 59000.0,
    "high": 60500.0,
    "low": 57200.0,
    "close": 59200.0,
    "volume": 388246.0
  },
  {
    "time": 1593356400,
    "open": 58900.0,
    "high": 58900.0,
    "low": 52400.0,
    "close": 56300.0,
    "volume": 561050.0
  },
  {
    "time": 1593961200,
    "open": 56000.0,
    "high": 59200.0,
    "low": 53100.0,
    "close": 55800.0,
    "volume": 681748.0
  },
  {
    "time": 1594566000,
    "open": 58000.0,
    "high": 58000.0,
    "low": 53700.0,
    "close": 57100.0,
    "volume": 479544.0
  },
  {
    "time": 1595170800,
    "open": 57000.0,
    "high": 60000.0,
    "low": 55500.0,
    "close": 58400.0,
    "volume": 503913.0
  },
  {
    "time": 1595775600,
    "open": 58100.0,
    "high": 64100.0,
    "low": 57700.0,
    "close": 59300.0,
    "volume": 941976.0
  },
  {
    "time": 1596380400,
    "open": 59700.0,
    "high": 61900.0,
    "low": 58600.0,
    "close": 61000.0,
    "volume": 347075.0
  },
  {
    "time": 1596985200,
    "open": 60800.0,
    "high": 66800.0,
    "low": 58100.0,
    "close": 64400.0,
    "volume": 867736.0
  },
  {
    "time": 1597676400,
    "open": 64500.0,
    "high": 77700.0,
    "low": 64300.0,
    "close": 67900.0,
    "volume": 2041994.0
  },
  {
    "time": 1598194800,
    "open": 68200.0,
    "high": 71500.0,
    "low": 67800.0,
    "close": 68200.0,
    "volume": 608287.0
  },
  {
    "time": 1598799600,
    "open": 68600.0,
    "high": 73300.0,
    "low": 67600.0,
    "close": 71000.0,
    "volume": 587631.0
  },
  {
    "time": 1599404400,
    "open": 70300.0,
    "high": 70800.0,
    "low": 65700.0,
    "close": 67000.0,
    "volume": 488709.0
  },
  {
    "time": 1600009200,
    "open": 67900.0,
    "high": 68900.0,
    "low": 66500.0,
    "close": 67800.0,
    "volume": 214483.0
  },
  {
    "time": 1600614000,
    "open": 67600.0,
    "high": 69400.0,
    "low": 57800.0,
    "close": 58200.0,
    "volume": 528016.0
  },
  {
    "time": 1601218800,
    "open": 58800.0,
    "high": 62200.0,
    "low": 57700.0,
    "close": 62000.0,
    "volume": 127789.0
  },
  {
    "time": 1601823600,
    "open": 61800.0,
    "high": 64800.0,
    "low": 61500.0,
    "close": 63000.0,
    "volume": 231557.0
  },
  {
    "time": 1602428400,
    "open": 63000.0,
    "high": 68800.0,
    "low": 61000.0,
    "close": 62900.0,
    "volume": 387191.0
  },
  {
    "time": 1603033200,
    "open": 63500.0,
    "high": 64800.0,
    "low": 60900.0,
    "close": 61800.0,
    "volume": 191924.0
  },
  {
    "time": 1603638000,
    "open": 61800.0,
    "high": 62300.0,
    "low": 58100.0,
    "close": 59800.0,
    "volume": 260825.0
  },
  {
    "time": 1604242800,
    "open": 59000.0,
    "high": 64500.0,
    "low": 58500.0,
    "close": 61600.0,
    "volume": 278102.0
  },
  {
    "time": 1604847600,
    "open": 63400.0,
    "high": 65300.0,
    "low": 59800.0,
    "close": 61300.0,
    "volume": 676929.0
  },
  {
    "time": 1605452400,
    "open": 61500.0,
    "high": 62100.0,
    "low": 58400.0,
    "close": 60300.0,
    "volume": 431487.0
  },
  {
    "time": 1606057200,
    "open": 61100.0,
    "high": 62500.0,
    "low": 58800.0,
    "close": 60800.0,
    "volume": 446756.0
  },
  {
    "time": 1606662000,
    "open": 60900.0,
    "high": 61200.0,
    "low": 56000.0,
    "close": 56600.0,
    "volume": 468180.0
  },
  {
    "time": 1607266800,
    "open": 56600.0,
    "high": 60900.0,
    "low": 55800.0,
    "close": 59800.0,
    "volume": 407389.0
  },
  {
    "time": 1607871600,
    "open": 59800.0,
    "high": 60100.0,
    "low": 58000.0,
    "close": 59000.0,
    "volume": 273468.0
  },
  {
    "time": 1608476400,
    "open": 58800.0,
    "high": 59000.0,
    "low": 55000.0,
    "close": 56200.0,
    "volume": 325731.0
  },
  {
    "time": 1609081200,
    "open": 56700.0,
    "high": 58600.0,
    "low": 56400.0,
    "close": 57200.0,
    "volume": 238398.0
  },
  {
    "time": 1609686000,
    "open": 57300.0,
    "high": 57700.0,
    "low": 53500.0,
    "close": 53900.0,
    "volume": 511589.0
  },
  {
    "time": 1610290800,
    "open": 54200.0,
    "high": 57700.0,
    "low": 54000.0,
    "close": 57000.0,
    "volume": 470902.0
  },
  {
    "time": 1610895600,
    "open": 56900.0,
    "high": 61500.0,
    "low": 55600.0,
    "close": 60500.0,
    "volume": 583503.0
  },
  {
    "time": 1611500400,
    "open": 61100.0,
    "high": 65400.0,
    "low": 58500.0,
    "close": 61600.0,
    "volume": 793459.0
  },
  {
    "time": 1612105200,
    "open": 62200.0,
    "high": 67000.0,
    "low": 60900.0,
    "close": 62400.0,
    "volume": 1115752.0
  },
  {
    "time": 1612710000,
    "open": 61600.0,
    "high": 65000.0,
    "low": 61000.0,
    "close": 64700.0,
    "volume": 253279.0
  },
  {
    "time": 1613314800,
    "open": 64900.0,
    "high": 64900.0,
    "low": 60000.0,
    "close": 60600.0,
    "volume": 385224.0
  },
  {
    "time": 1613919600,
    "open": 61800.0,
    "high": 63400.0,
    "low": 55300.0,
    "close": 56200.0,
    "volume": 658175.0
  },
  {
    "time": 1614610800,
    "open": 57400.0,
    "high": 61400.0,
    "low": 55800.0,
    "close": 61300.0,
    "volume": 280359.0
  },
  {
    "time": 1615129200,
    "open": 61300.0,
    "high": 61700.0,
    "low": 57300.0,
    "close": 58500.0,
    "volume": 210015.0
  },
  {
    "time": 1615734000,
    "open": 59000.0,
    "high": 62300.0,
    "low": 57500.0,
    "close": 61500.0,
    "volume": 362033.0
  },
  {
    "time": 1616338800,
    "open": 62000.0,
    "high": 72200.0,
    "low": 61300.0,
    "close": 68100.0,
    "volume": 1507575.0
  },
  {
    "time": 1616943600,
    "open": 67800.0,
    "high": 71900.0,
    "low": 65000.0,
    "close": 69900.0,
    "volume": 755416.0
  },
  {
    "time": 1617548400,
    "open": 69300.0,
    "high": 71300.0,
    "low": 67000.0,
    "close": 69600.0,
    "volume": 483440.0
  },
  {
    "time": 1618153200,
    "open": 70600.0,
    "high": 75500.0,
    "low": 69500.0,
    "close": 72100.0,
    "volume": 731631.0
  },
  {
    "time": 1618758000,
    "open": 72100.0,
    "high": 74500.0,
    "low": 70500.0,
    "close": 72100.0,
    "volume": 480922.0
  },
  {
    "time": 1619362800,
    "open": 72900.0,
    "high": 76500.0,
    "low": 69300.0,
    "close": 70000.0,
    "volume": 518217.0
  },
  {
    "time": 1619967600,
    "open": 69300.0,
    "high": 71100.0,
    "low": 65300.0,
    "close": 69400.0,
    "volume": 340632.0
  },
  {
    "time": 1620572400,
    "open": 69500.0,
    "high": 73500.0,
    "low": 67700.0,
    "close": 73000.0,
    "volume": 410364.0
  },
  {
    "time": 1621177200,
    "open": 75900.0,
    "high": 81300.0,
    "low": 75100.0,
    "close": 79300.0,
    "volume": 1025160.0
  },
  {
    "time": 1621782000,
    "open": 78300.0,
    "high": 85000.0,
    "low": 77400.0,
    "close": 83300.0,
    "volume": 623535.0
  },
  {
    "time": 1622386800,
    "open": 83800.0,
    "high": 86000.0,
    "low": 80600.0,
    "close": 81400.0,
    "volume": 634512.0
  },
  {
    "time": 1622991600,
    "open": 81500.0,
    "high": 94100.0,
    "low": 80700.0,
    "close": 92300.0,
    "volume": 892893.0
  },
  {
    "time": 1623596400,
    "open": 92700.0,
    "high": 95100.0,
    "low": 90500.0,
    "close": 93600.0,
    "volume": 443551.0
  },
  {
    "time": 1624201200,
    "open": 92800.0,
    "high": 94500.0,
    "low": 84000.0,
    "close": 87800.0,
    "volume": 757341.0
  },
  {
    "time": 1624806000,
    "open": 88300.0,
    "high": 91900.0,
    "low": 87300.0,
    "close": 88500.0,
    "volume": 503641.0
  },
  {
    "time": 1625410800,
    "open": 88500.0,
    "high": 90400.0,
    "low": 83300.0,
    "close": 85200.0,
    "volume": 580344.0
  },
  {
    "time": 1626015600,
    "open": 86000.0,
    "high": 91400.0,
    "low": 82200.0,
    "close": 88000.0,
    "volume": 572378.0
  },
  {
    "time": 1626620400,
    "open": 87100.0,
    "high": 89100.0,
    "low": 83200.0,
    "close": 88400.0,
    "volume": 529198.0
  },
  {
    "time": 1627225200,
    "open": 89200.0,
    "high": 90000.0,
    "low": 84000.0,
    "close": 88800.0,
    "volume": 496454.0
  },
  {
    "time": 1627830000,
    "open": 89000.0,
    "high": 93200.0,
    "low": 88500.0,
    "close": 89700.0,
    "volume": 515451.0
  },
  {
    "time": 1628434800,
    "open": 89700.0,
    "high": 97900.0,
    "low": 88100.0,
    "close": 97000.0,
    "volume": 641920.0
  },
  {
    "time": 1629126000,
    "open": 98800.0,
    "high": 101700.0,
    "low": 89000.0,
    "close": 90300.0,
    "volume": 1220180.0
  },
  {
    "time": 1629644400,
    "open": 91900.0,
    "high": 100900.0,
    "low": 91300.0,
    "close": 97800.0,
    "volume": 918789.0
  },
  {
    "time": 1630249200,
    "open": 98100.0,
    "high": 99600.0,
    "low": 95800.0,
    "close": 96600.0,
    "volume": 494620.0
  },
  {
    "time": 1630854000,
    "open": 96600.0,
    "high": 96800.0,
    "low": 90700.0,
    "close": 92900.0,
    "volume": 481160.0
  },
  {
    "time": 1631458800,
    "open": 92400.0,
    "high": 94500.0,
    "low": 90300.0,
    "close": 91800.0,
    "volume": 541119.0
  },
  {
    "time": 1632322800,
    "open": 90800.0,
    "high": 92200.0,
    "low": 87900.0,
    "close": 89700.0,
    "volume": 206143.0
  },
  {
    "time": 1632668400,
    "open": 90200.0,
    "high": 90500.0,
    "low": 81100.0,
    "close": 81900.0,
    "volume": 528541.0
  },
  {
    "time": 1633359600,
    "open": 81900.0,
    "high": 85600.0,
    "low": 78100.0,
    "close": 82500.0,
    "volume": 515789.0
  },
  {
    "time": 1633964400,
    "open": 82900.0,
    "high": 88500.0,
    "low": 80900.0,
    "close": 86700.0,
    "volume": 258095.0
  },
  {
    "time": 1634482800,
    "open": 86000.0,
    "high": 92000.0,
    "low": 84300.0,
    "close": 88100.0,
    "volume": 317808.0
  },
  {
    "time": 1635087600,
    "open": 88100.0,
    "high": 94700.0,
    "low": 87000.0,
    "close": 92000.0,
    "volume": 364837.0
  },
  {
    "time": 1635692400,
    "open": 92600.0,
    "high": 92600.0,
    "low": 85100.0,
    "close": 88300.0,
    "volume": 250346.0
  },
  {
    "time": 1636297200,
    "open": 88300.0,
    "high": 90500.0,
    "low": 73000.0,
    "close": 79900.0,
    "volume": 966179.0
  },
  {
    "time": 1636902000,
    "open": 80000.0,
    "high": 82000.0,
    "low": 75200.0,
    "close": 76600.0,
    "volume": 396200.0
  },
  {
    "time": 1637506800,
    "open": 76700.0,
    "high": 80500.0,
    "low": 75600.0,
    "close": 79000.0,
    "volume": 410419.0
  },
  {
    "time": 1638111600,
    "open": 77500.0,
    "high": 82000.0,
    "low": 72600.0,
    "close": 78900.0,
    "volume": 471585.0
  },
  {
    "time": 1638716400,
    "open": 77900.0,
    "high": 82000.0,
    "low": 74700.0,
    "close": 78500.0,
    "volume": 381118.0
  },
  {
    "time": 1639321200,
    "open": 78500.0,
    "high": 79400.0,
    "low": 76200.0,
    "close": 76800.0,
    "volume": 197515.0
  },
  {
    "time": 1639926000,
    "open": 76500.0,
    "high": 80100.0,
    "low": 75900.0,
    "close": 78000.0,
    "volume": 231433.0
  },
  {
    "time": 1640530800,
    "open": 77900.0,
    "high": 84800.0,
    "low": 77500.0,
    "close": 82000.0,
    "volume": 340153.0
  },
  {
    "time": 1641135600,
    "open": 83000.0,
    "high": 83000.0,
    "low": 76700.0,
    "close": 78300.0,
    "volume": 230322.0
  },
  {
    "time": 1641740400,
    "open": 78300.0,
    "high": 80700.0,
    "low": 76300.0,
    "close": 79000.0,
    "volume": 256905.0
  },
  {
    "time": 1642345200,
    "open": 79500.0,
    "high": 80100.0,
    "low": 76000.0,
    "close": 76700.0,
    "volume": 275275.0
  },
  {
    "time": 1642950000,
    "open": 76700.0,
    "high": 77500.0,
    "low": 72500.0,
    "close": 75400.0,
    "volume": 294005.0
  },
  {
    "time": 1643814000,
    "open": 76500.0,
    "high": 78600.0,
    "low": 75700.0,
    "close": 78100.0,
    "volume": 76262.0
  },
  {
    "time": 1644159600,
    "open": 77700.0,
    "high": 82200.0,
    "low": 76100.0,
    "close": 78500.0,
    "volume": 276774.0
  },
  {
    "time": 1644764400,
    "open": 78400.0,
    "high": 88400.0,
    "low": 76300.0,
    "close": 85100.0,
    "volume": 600302.0
  },
  {
    "time": 1645369200,
    "open": 83700.0,
    "high": 89500.0,
    "low": 83200.0,
    "close": 87100.0,
    "volume": 375078.0
  },
  {
    "time": 1645974000,
    "open": 87200.0,
    "high": 88700.0,
    "low": 84700.0,
    "close": 87100.0,
    "volume": 190969.0
  },
  {
    "time": 1646578800,
    "open": 86100.0,
    "high": 88700.0,
    "low": 82900.0,
    "close": 88000.0,
    "volume": 236212.0
  },
  {
    "time": 1647183600,
    "open": 87700.0,
    "high": 93700.0,
    "low": 85100.0,
    "close": 92000.0,
    "volume": 397927.0
  },
  {
    "time": 1647788400,
    "open": 92000.0,
    "high": 93100.0,
    "low": 90300.0,
    "close": 91900.0,
    "volume": 195707.0
  },
  {
    "time": 1648393200,
    "open": 91700.0,
    "high": 94700.0,
    "low": 89400.0,
    "close": 93000.0,
    "volume": 262213.0
  },
  {
    "time": 1648998000,
    "open": 94800.0,
    "high": 99900.0,
    "low": 92500.0,
    "close": 98400.0,
    "volume": 509606.0
  },
  {
    "time": 1649602800,
    "open": 99000.0,
    "high": 99000.0,
    "low": 94500.0,
    "close": 97300.0,
    "volume": 268207.0
  },
  {
    "time": 1650207600,
    "open": 97900.0,
    "high": 99500.0,
    "low": 91900.0,
    "close": 94700.0,
    "volume": 295904.0
  },
  {
    "time": 1650812400,
    "open": 94000.0,
    "high": 94000.0,
    "low": 89300.0,
    "close": 93000.0,
    "volume": 275413.0
  },
  {
    "time": 1651417200,
    "open": 91600.0,
    "high": 92000.0,
    "low": 84600.0,
    "close": 87500.0,
    "volume": 236572.0
  },
  {
    "time": 1652022000,
    "open": 86600.0,
    "high": 86600.0,
    "low": 77100.0,
    "close": 82100.0,
    "volume": 440622.0
  },
  {
    "time": 1652626800,
    "open": 82800.0,
    "high": 83100.0,
    "low": 77300.0,
    "close": 81600.0,
    "volume": 260325.0
  },
  {
    "time": 1653231600,
    "open": 81600.0,
    "high": 84400.0,
    "low": 78500.0,
    "close": 82900.0,
    "volume": 285402.0
  },
  {
    "time": 1653836400,
    "open": 83800.0,
    "high": 84500.0,
    "low": 79600.0,
    "close": 80200.0,
    "volume": 206898.0
  },
  {
    "time": 1654527600,
    "open": 80100.0,
    "high": 80200.0,
    "low": 75500.0,
    "close": 76500.0,
    "volume": 234656.0
  },
  {
    "time": 1655046000,
    "open": 74900.0,
    "high": 74900.0,
    "low": 67900.0,
    "close": 72200.0,
    "volume": 317369.0
  },
  {
    "time": 1655650800,
    "open": 72000.0,
    "high": 73700.0,
    "low": 68800.0,
    "close": 73400.0,
    "volume": 265240.0
  },
  {
    "time": 1656255600,
    "open": 72700.0,
    "high": 74100.0,
    "low": 65000.0,
    "close": 65700.0,
    "volume": 332379.0
  },
  {
    "time": 1656860400,
    "open": 66200.0,
    "high": 67700.0,
    "low": 64200.0,
    "close": 65600.0,
    "volume": 251529.0
  },
  {
    "time": 1657465200,
    "open": 65600.0,
    "high": 69300.0,
    "low": 62000.0,
    "close": 64400.0,
    "volume": 464189.0
  },
  {
    "time": 1658070000,
    "open": 64900.0,
    "high": 68100.0,
    "low": 64200.0,
    "close": 65100.0,
    "volume": 346976.0
  },
  {
    "time": 1658674800,
    "open": 65800.0,
    "high": 73800.0,
    "low": 64900.0,
    "close": 72600.0,
    "volume": 483587.0
  },
  {
    "time": 1659279600,
    "open": 72400.0,
    "high": 72400.0,
    "low": 69600.0,
    "close": 72000.0,
    "volume": 225922.0
  },
  {
    "time": 1659884400,
    "open": 71500.0,
    "high": 71500.0,
    "low": 67500.0,
    "close": 69000.0,
    "volume": 285463.0
  },
  {
    "time": 1660575600,
    "open": 69400.0,
    "high": 74700.0,
    "low": 68800.0,
    "close": 69800.0,
    "volume": 499319.0
  },
  {
    "time": 1661094000,
    "open": 68500.0,
    "high": 69500.0,
    "low": 66000.0,
    "close": 66300.0,
    "volume": 200355.0
  },
  {
    "time": 1661698800,
    "open": 64200.0,
    "high": 67800.0,
    "low": 63300.0,
    "close": 65500.0,
    "volume": 249337.0
  },
  {
    "time": 1662303600,
    "open": 65100.0,
    "high": 66500.0,
    "low": 62600.0,
    "close": 64100.0,
    "volume": 194643.0
  },
  {
    "time": 1662994800,
    "open": 65500.0,
    "high": 65900.0,
    "low": 62300.0,
    "close": 62400.0,
    "volume": 153314.0
  },
  {
    "time": 1663513200,
    "open": 62300.0,
    "high": 63800.0,
    "low": 59800.0,
    "close": 60000.0,
    "volume": 206864.0
  },
  {
    "time": 1664118000,
    "open": 59500.0,
    "high": 59800.0,
    "low": 55000.0,
    "close": 56600.0,
    "volume": 263694.0
  },
  {
    "time": 1664809200,
    "open": 57100.0,
    "high": 61100.0,
    "low": 56800.0,
    "close": 59700.0,
    "volume": 152969.0
  },
  {
    "time": 1665414000,
    "open": 58400.0,
    "high": 59500.0,
    "low": 55000.0,
    "close": 59000.0,
    "volume": 161611.0
  },
  {
    "time": 1665932400,
    "open": 57600.0,
    "high": 60200.0,
    "low": 56800.0,
    "close": 58400.0,
    "volume": 162884.0
  },
  {
    "time": 1666537200,
    "open": 61300.0,
    "high": 62500.0,
    "low": 59500.0,
    "close": 59900.0,
    "volume": 215855.0
  },
  {
    "time": 1667142000,
    "open": 60500.0,
    "high": 62800.0,
    "low": 59800.0,
    "close": 61400.0,
    "volume": 137600.0
  },
  {
    "time": 1667746800,
    "open": 61300.0,
    "high": 66000.0,
    "low": 60900.0,
    "close": 64600.0,
    "volume": 238763.0
  },
  {
    "time": 1668351600,
    "open": 64200.0,
    "high": 67000.0,
    "low": 60500.0,
    "close": 66000.0,
    "volume": 422487.0
  },
  {
    "time": 1668956400,
    "open": 65900.0,
    "high": 67100.0,
    "low": 63700.0,
    "close": 65500.0,
    "volume": 185528.0
  },
  {
    "time": 1669561200,
    "open": 65500.0,
    "high": 69700.0,
    "low": 63100.0,
    "close": 66500.0,
    "volume": 247757.0
  },
  {
    "time": 1670166000,
    "open": 67100.0,
    "high": 69800.0,
    "low": 66200.0,
    "close": 68700.0,
    "volume": 247574.0
  },
  {
    "time": 1670770800,
    "open": 68100.0,
    "high": 69800.0,
    "low": 66900.0,
    "close": 67500.0,
    "volume": 230818.0
  },
  {
    "time": 1671375600,
    "open": 67000.0,
    "high": 70800.0,
    "low": 66600.0,
    "close": 67800.0,
    "volume": 220710.0
  },
  {
    "time": 1671980400,
    "open": 68200.0,
    "high": 71800.0,
    "low": 67200.0,
    "close": 69900.0,
    "volume": 344101.0
  },
  {
    "time": 1672585200,
    "open": 70100.0,
    "high": 70900.0,
    "low": 65100.0,
    "close": 66200.0,
    "volume": 305398.0
  },
  {
    "time": 1673190000,
    "open": 66700.0,
    "high": 69200.0,
    "low": 66300.0,
    "close": 67600.0,
    "volume": 211378.0
  },
  {
    "time": 1673794800,
    "open": 67700.0,
    "high": 77400.0,
    "low": 66900.0,
    "close": 77400.0,
    "volume": 506070.0
  },
  {
    "time": 1674572400,
    "open": 77400.0,
    "high": 79800.0,
    "low": 75000.0,
    "close": 75900.0,
    "volume": 278115.0
  },
  {
    "time": 1675004400,
    "open": 75300.0,
    "high": 78700.0,
    "low": 74200.0,
    "close": 77600.0,
    "volume": 337267.0
  },
  {
    "time": 1675609200,
    "open": 76400.0,
    "high": 78500.0,
    "low": 73800.0,
    "close": 74500.0,
    "volume": 280904.0
  },
  {
    "time": 1676214000,
    "open": 74500.0,
    "high": 77100.0,
    "low": 73400.0,
    "close": 75700.0,
    "volume": 278161.0
  },
  {
    "time": 1676818800,
    "open": 75800.0,
    "high": 77500.0,
    "low": 72600.0,
    "close": 73200.0,
    "volume": 177472.0
  },
  {
    "time": 1677423600,
    "open": 72100.0,
    "high": 77400.0,
    "low": 72000.0,
    "close": 76700.0,
    "volume": 222895.0
  },
  {
    "time": 1678028400,
    "open": 77000.0,
    "high": 77700.0,
    "low": 71600.0,
    "close": 71900.0,
    "volume": 220050.0
  },
  {
    "time": 1678633200,
    "open": 71700.0,
    "high": 73100.0,
    "low": 68500.0,
    "close": 70600.0,
    "volume": 273631.0
  },
  {
    "time": 1679238000,
    "open": 70600.0,
    "high": 72200.0,
    "low": 67000.0,
    "close": 69300.0,
    "volume": 235698.0
  },
  {
    "time": 1679842800,
    "open": 69200.0,
    "high": 71200.0,
    "low": 68000.0,
    "close": 70200.0,
    "volume": 334418.0
  },
  {
    "time": 1680447600,
    "open": 70900.0,
    "high": 90600.0,
    "low": 70900.0,
    "close": 86800.0,
    "volume": 1693090.0
  },
  {
    "time": 1681052400,
    "open": 86300.0,
    "high": 97800.0,
    "low": 83000.0,
    "close": 96200.0,
    "volume": 977272.0
  },
  {
    "time": 1681657200,
    "open": 96400.0,
    "high": 109200.0,
    "low": 95600.0,
    "close": 99100.0,
    "volume": 1053632.0
  },
  {
    "time": 1682262000,
    "open": 99100.0,
    "high": 104700.0,
    "low": 97200.0,
    "close": 101000.0,
    "volume": 493314.0
  },
  {
    "time": 1682953200,
    "open": 102300.0,
    "high": 106600.0,
    "low": 98000.0,
    "close": 100900.0,
    "volume": 478950.0
  },
  {
    "time": 1683471600,
    "open": 100900.0,
    "high": 105200.0,
    "low": 97000.0,
    "close": 97500.0,
    "volume": 600339.0
  },
  {
    "time": 1684076400,
    "open": 97700.0,
    "high": 123800.0,
    "low": 97000.0,
    "close": 117600.0,
    "volume": 1460133.0
  },
  {
    "time": 1684681200,
    "open": 116100.0,
    "high": 118200.0,
    "low": 111100.0,
    "close": 114800.0,
    "volume": 490074.0
  },
  {
    "time": 1685372400,
    "open": 116000.0,
    "high": 126100.0,
    "low": 110800.0,
    "close": 122500.0,
    "volume": 565971.0
  },
  {
    "time": 1685890800,
    "open": 122600.0,
    "high": 131200.0,
    "low": 119900.0,
    "close": 130000.0,
    "volume": 518144.0
  },
  {
    "time": 1686495600,
    "open": 132700.0,
    "high": 140600.0,
    "low": 131200.0,
    "close": 138200.0,
    "volume": 685567.0
  },
  {
    "time": 1687100400,
    "open": 138200.0,
    "high": 145800.0,
    "low": 134000.0,
    "close": 139500.0,
    "volume": 464272.0
  },
  {
    "time": 1687705200,
    "open": 138600.0,
    "high": 147000.0,
    "low": 134100.0,
    "close": 143700.0,
    "volume": 469072.0
  },
  {
    "time": 1688310000,
    "open": 143800.0,
    "high": 143800.0,
    "low": 126000.0,
    "close": 127700.0,
    "volume": 985492.0
  },
  {
    "time": 1688914800,
    "open": 127800.0,
    "high": 133100.0,
    "low": 121200.0,
    "close": 130500.0,
    "volume": 440193.0
  },
  {
    "time": 1689519600,
    "open": 129000.0,
    "high": 129000.0,
    "low": 118300.0,
    "close": 124500.0,
    "volume": 555257.0
  },
  {
    "time": 1690124400,
    "open": 124500.0,
    "high": 133200.0,
    "low": 117400.0,
    "close": 126900.0,
    "volume": 682550.0
  },
  {
    "time": 1690729200,
    "open": 129000.0,
    "high": 147000.0,
    "low": 127700.0,
    "close": 140100.0,
    "volume": 1034950.0
  },
  {
    "time": 1691334000,
    "open": 140100.0,
    "high": 158200.0,
    "low": 135700.0,
    "close": 149000.0,
    "volume": 1123636.0
  },
  {
    "time": 1691938800,
    "open": 142900.0,
    "high": 153900.0,
    "low": 135000.0,
    "close": 136900.0,
    "volume": 869972.0
  },
  {
    "time": 1692543600,
    "open": 138900.0,
    "high": 146500.0,
    "low": 133800.0,
    "close": 140800.0,
    "volume": 610563.0
  },
  {
    "time": 1693148400,
    "open": 144500.0,
    "high": 147400.0,
    "low": 131000.0,
    "close": 132900.0,
    "volume": 934530.0
  },
  {
    "time": 1693753200,
    "open": 136000.0,
    "high": 136000.0,
    "low": 124300.0,
    "close": 129500.0,
    "volume": 985653.0
  },
  {
    "time": 1694358000,
    "open": 130100.0,
    "high": 132400.0,
    "low": 122600.0,
    "close": 128000.0,
    "volume": 538987.0
  },
  {
    "time": 1694962800,
    "open": 127000.0,
    "high": 127100.0,
    "low": 115300.0,
    "close": 117600.0,
    "volume": 558404.0
  },
  {
    "time": 1695567600,
    "open": 116700.0,
    "high": 128200.0,
    "low": 116700.0,
    "close": 126500.0,
    "volume": 399024.0
  },
  {
    "time": 1696345200,
    "open": 125700.0,
    "high": 126300.0,
    "low": 117500.0,
    "close": 125100.0,
    "volume": 334220.0
  },
  {
    "time": 1696863600,
    "open": 124400.0,
    "high": 125100.0,
    "low": 110000.0,
    "close": 112400.0,
    "volume": 610853.0
  },
  {
    "time": 1697382000,
    "open": 111500.0,
    "high": 116000.0,
    "low": 103400.0,
    "close": 106700.0,
    "volume": 500769.0
  },
  {
    "time": 1697986800,
    "open": 106000.0,
    "high": 118400.0,
    "low": 106000.0,
    "close": 116600.0,
    "volume": 380560.0
  },
  {
    "time": 1698591600,
    "open": 117500.0,
    "high": 123700.0,
    "low": 115100.0,
    "close": 118500.0,
    "volume": 344594.0
  },
  {
    "time": 1699196400,
    "open": 120000.0,
    "high": 125500.0,
    "low": 110600.0,
    "close": 121700.0,
    "volume": 630684.0
  },
  {
    "time": 1699801200,
    "open": 122900.0,
    "high": 125500.0,
    "low": 110400.0,
    "close": 115500.0,
    "volume": 902109.0
  },
  {
    "time": 1700406000,
    "open": 116900.0,
    "high": 116900.0,
    "low": 109000.0,
    "close": 113000.0,
    "volume": 465015.0
  },
  {
    "time": 1701010800,
    "open": 113200.0,
    "high": 113300.0,
    "low": 105800.0,
    "close": 106300.0,
    "volume": 339328.0
  },
  {
    "time": 1701615600,
    "open": 107500.0,
    "high": 107500.0,
    "low": 101700.0,
    "close": 104500.0,
    "volume": 415544.0
  },
  {
    "time": 1702220400,
    "open": 105500.0,
    "high": 109100.0,
    "low": 103800.0,
    "close": 105500.0,
    "volume": 408340.0
  },
  {
    "time": 1702825200,
    "open": 105600.0,
    "high": 113100.0,
    "low": 105300.0,
    "close": 110000.0,
    "volume": 349065.0
  },
  {
    "time": 1703516400,
    "open": 110700.0,
    "high": 111600.0,
    "low": 106800.0,
    "close": 109500.0,
    "volume": 157719.0
  },
  {
    "time": 1704121200,
    "open": 108400.0,
    "high": 111800.0,
    "low": 105500.0,
    "close": 106200.0,
    "volume": 218776.0
  },
  {
    "time": 1704639600,
    "open": 106400.0,
    "high": 124000.0,
    "low": 104900.0,
    "close": 120300.0,
    "volume": 705605.0
  },
  {
    "time": 1705244400,
    "open": 120600.0,
    "high": 122300.0,
    "low": 112600.0,
    "close": 117200.0,
    "volume": 354313.0
  },
  {
    "time": 1705849200,
    "open": 118700.0,
    "high": 118700.0,
    "low": 109500.0,
    "close": 112400.0,
    "volume": 340546.0
  },
  {
    "time": 1706454000,
    "open": 112400.0,
    "high": 113400.0,
    "low": 100200.0,
    "close": 101300.0,
    "volume": 444766.0
  },
  {
    "time": 1707058800,
    "open": 101000.0,
    "high": 103900.0,
    "low": 98100.0,
    "close": 103300.0,
    "volume": 318582.0
  },
  {
    "time": 1707750000,
    "open": 101400.0,
    "high": 102100.0,
    "low": 93600.0,
    "close": 96600.0,
    "volume": 473804.0
  },
  {
    "time": 1708268400,
    "open": 96800.0,
    "high": 97500.0,
    "low": 90600.0,
    "close": 94700.0,
    "volume": 508127.0
  },
  {
    "time": 1708873200,
    "open": 94400.0,
    "high": 98300.0,
    "low": 91300.0,
    "close": 93900.0,
    "volume": 308160.0
  },
  {
    "time": 1709478000,
    "open": 94100.0,
    "high": 95800.0,
    "low": 86800.0,
    "close": 89200.0,
    "volume": 458340.0
  },
  {
    "time": 1710082800,
    "open": 89200.0,
    "high": 94400.0,
    "low": 88000.0,
    "close": 91300.0,
    "volume": 352141.0
  },
  {
    "time": 1710687600,
    "open": 91300.0,
    "high": 94400.0,
    "low": 90500.0,
    "close": 91000.0,
    "volume": 273442.0
  },
  {
    "time": 1711292400,
    "open": 91300.0,
    "high": 105300.0,
    "low": 90800.0,
    "close": 100900.0,
    "volume": 972041.0
  },
  {
    "time": 1711897200,
    "open": 99700.0,
    "high": 119000.0,
    "low": 98600.0,
    "close": 113600.0,
    "volume": 1568448.0
  },
  {
    "time": 1712502000,
    "open": 114500.0,
    "high": 130000.0,
    "low": 107000.0,
    "close": 127300.0,
    "volume": 1276541.0
  },
  {
    "time": 1713106800,
    "open": 126400.0,
    "high": 132900.0,
    "low": 119000.0,
    "close": 129500.0,
    "volume": 1079900.0
  },
  {
    "time": 1713711600,
    "open": 129500.0,
    "high": 132600.0,
    "low": 107700.0,
    "close": 118800.0,
    "volume": 1470805.0
  },
  {
    "time": 1714316400,
    "open": 122300.0,
    "high": 143000.0,
    "low": 121600.0,
    "close": 139600.0,
    "volume": 1163485.0
  },
  {
    "time": 1715007600,
    "open": 139000.0,
    "high": 146900.0,
    "low": 127400.0,
    "close": 143000.0,
    "volume": 1288027.0
  },
  {
    "time": 1715526000,
    "open": 143000.0,
    "high": 149600.0,
    "low": 132400.0,
    "close": 137700.0,
    "volume": 1557707.0
  },
  {
    "time": 1716130800,
    "open": 137400.0,
    "high": 142100.0,
    "low": 128900.0,
    "close": 138200.0,
    "volume": 972926.0
  },
  {
    "time": 1716735600,
    "open": 138400.0,
    "high": 146700.0,
    "low": 129900.0,
    "close": 146100.0,
    "volume": 1103144.0
  },
  {
    "time": 1717340400,
    "open": 145800.0,
    "high": 145800.0,
    "low": 126100.0,
    "close": 130800.0,
    "volume": 1084351.0
  },
  {
    "time": 1717945200,
    "open": 131000.0,
    "high": 141500.0,
    "low": 126500.0,
    "close": 131800.0,
    "volume": 874984.0
  },
  {
    "time": 1718550000,
    "open": 135000.0,
    "high": 144600.0,
    "low": 133900.0,
    "close": 143800.0,
    "volume": 969577.0
  },
  {
    "time": 1719154800,
    "open": 149300.0,
    "high": 157100.0,
    "low": 146000.0,
    "close": 148800.0,
    "volume": 1555569.0
  },
  {
    "time": 1719759600,
    "open": 151500.0,
    "high": 157400.0,
    "low": 135300.0,
    "close": 139200.0,
    "volume": 871997.0
  },
  {
    "time": 1720364400,
    "open": 141400.0,
    "high": 151500.0,
    "low": 140500.0,
    "close": 147800.0,
    "volume": 649327.0
  },
  {
    "time": 1720969200,
    "open": 147800.0,
    "high": 153700.0,
    "low": 138700.0,
    "close": 141300.0,
    "volume": 582597.0
  },
  {
    "time": 1721574000,
    "open": 141300.0,
    "high": 147800.0,
    "low": 132000.0,
    "close": 133000.0,
    "volume": 493037.0
  },
  {
    "time": 1722178800,
    "open": 133500.0,
    "high": 151800.0,
    "low": 132200.0,
    "close": 143200.0,
    "volume": 747278.0
  },
  {
    "time": 1722783600,
    "open": 138000.0,
    "high": 179200.0,
    "low": 121300.0,
    "close": 172000.0,
    "volume": 2728922.0
  },
  {
    "time": 1723388400,
    "open": 171900.0,
    "high": 189500.0,
    "low": 169000.0,
    "close": 188100.0,
    "volume": 1141641.0
  },
  {
    "time": 1723993200,
    "open": 189000.0,
    "high": 190800.0,
    "low": 174500.0,
    "close": 179000.0,
    "volume": 839734.0
  },
  {
    "time": 1724598000,
    "open": 180000.0,
    "high": 180100.0,
    "low": 168000.0,
    "close": 174500.0,
    "volume": 837980.0
  },
  {
    "time": 1725202800,
    "open": 174500.0,
    "high": 197800.0,
    "low": 165300.0,
    "close": 186600.0,
    "volume": 2400205.0
  },
  {
    "time": 1725807600,
    "open": 182100.0,
    "high": 204000.0,
    "low": 180400.0,
    "close": 188100.0,
    "volume": 1953077.0
  },
  {
    "time": 1726671600,
    "open": 192800.0,
    "high": 205500.0,
    "low": 191100.0,
    "close": 201000.0,
    "volume": 553528.0
  },
  {
    "time": 1727017200,
    "open": 203000.0,
    "high": 208500.0,
    "low": 190300.0,
    "close": 192500.0,
    "volume": 803973.0
  },
  {
    "time": 1727622000,
    "open": 192600.0,
    "high": 201000.0,
    "low": 187400.0,
    "close": 201000.0,
    "volume": 450092.0
  },
  {
    "time": 1728226800,
    "open": 204000.0,
    "high": 217500.0,
    "low": 201000.0,
    "close": 212000.0,
    "volume": 569007.0
  },
  {
    "time": 1728831600,
    "open": 213000.0,
    "high": 232000.0,
    "low": 205000.0,
    "close": 227000.0,
    "volume": 595778.0
  },
  {
    "time": 1729436400,
    "open": 228500.0,
    "high": 238000.0,
    "low": 218500.0,
    "close": 233000.0,
    "volume": 673737.0
  },
  {
    "time": 1730041200,
    "open": 234000.0,
    "high": 241500.0,
    "low": 211500.0,
    "close": 213000.0,
    "volume": 662559.0
  },
  {
    "time": 1730646000,
    "open": 215000.0,
    "high": 236500.0,
    "low": 209500.0,
    "close": 219000.0,
    "volume": 739817.0
  },
  {
    "time": 1731250800,
    "open": 216000.0,
    "high": 229000.0,
    "low": 205000.0,
    "close": 219000.0,
    "volume": 897481.0
  },
  {
    "time": 1731855600,
    "open": 217000.0,
    "high": 220000.0,
    "low": 191600.0,
    "close": 198400.0,
    "volume": 749059.0
  },
  {
    "time": 1732460400,
    "open": 196600.0,
    "high": 212000.0,
    "low": 192100.0,
    "close": 198000.0,
    "volume": 536845.0
  },
  {
    "time": 1733065200,
    "open": 201500.0,
    "high": 227500.0,
    "low": 200500.0,
    "close": 213500.0,
    "volume": 783797.0
  },
  {
    "time": 1733670000,
    "open": 206500.0,
    "high": 248500.0,
    "low": 206000.0,
    "close": 245000.0,
    "volume": 836542.0
  },
  {
    "time": 1734274800,
    "open": 262500.0,
    "high": 267000.0,
    "low": 246000.0,
    "close": 253500.0,
    "volume": 739985.0
  },
  {
    "time": 1734879600,
    "open": 256000.0,
    "high": 270000.0,
    "low": 249500.0,
    "close": 255500.0,
    "volume": 449822.0
  },
  {
    "time": 1735484400,
    "open": 254500.0,
    "high": 273500.0,
    "low": 251000.0,
    "close": 260500.0,
    "volume": 373951.0
  },
  {
    "time": 1736089200,
    "open": 257000.0,
    "high": 261000.0,
    "low": 241000.0,
    "close": 251000.0,
    "volume": 616151.0
  },
  {
    "time": 1736694000,
    "open": 246000.0,
    "high": 267500.0,
    "low": 244000.0,
    "close": 263500.0,
    "volume": 623059.0
  },
  {
    "time": 1737298800,
    "open": 263500.0,
    "high": 265500.0,
    "low": 237500.0,
    "close": 243500.0,
    "volume": 653052.0
  },
  {
    "time": 1738249200,
    "open": 243000.0,
    "high": 245000.0,
    "low": 233500.0,
    "close": 241500.0,
    "volume": 104368.0
  },
  {
    "time": 1738508400,
    "open": 236500.0,
    "high": 272000.0,
    "low": 235500.0,
    "close": 266000.0,
    "volume": 531687.0
  },
  {
    "time": 1739113200,
    "open": 265000.0,
    "high": 294000.0,
    "low": 263500.0,
    "close": 286500.0,
    "volume": 733613.0
  },
  {
    "time": 1739718000,
    "open": 280000.0,
    "high": 297000.0,
    "low": 272500.0,
    "close": 288000.0,
    "volume": 567785.0
  },
  {
    "time": 1740322800,
    "open": 284000.0,
    "high": 301500.0,
    "low": 276500.0,
    "close": 291000.0,
    "volume": 416969.0
  },
  {
    "time": 1741014000,
    "open": 299500.0,
    "high": 327500.0,
    "low": 293000.0,
    "close": 305000.0,
    "volume": 557095.0
  },
  {
    "time": 1741532400,
    "open": 303000.0,
    "high": 336500.0,
    "low": 302000.0,
    "close": 335500.0,
    "volume": 437568.0
  },
  {
    "time": 1742137200,
    "open": 340000.0,
    "high": 345000.0,
    "low": 310000.0,
    "close": 327000.0,
    "volume": 348365.0
  },
  {
    "time": 1742742000,
    "open": 324000.0,
    "high": 341500.0,
    "low": 310500.0,
    "close": 337500.0,
    "volume": 302006.0
  },
  {
    "time": 1743346800,
    "open": 334500.0,
    "high": 356500.0,
    "low": 325000.0,
    "close": 335500.0,
    "volume": 456550.0
  },
  {
    "time": 1743951600,
    "open": 318000.0,
    "high": 369000.0,
    "low": 308000.0,
    "close": 366000.0,
    "volume": 528430.0
  },
  {
    "time": 1744556400,
    "open": 369500.0,
    "high": 374000.0,
    "low": 356500.0,
    "close": 367500.0,
    "volume": 257044.0
  },
  {
    "time": 1745161200,
    "open": 365000.0,
    "high": 380000.0,
    "low": 353000.0,
    "close": 375500.0,
    "volume": 343391.0
  },
  {
    "time": 1745766000,
    "open": 379500.0,
    "high": 395000.0,
    "low": 372000.0,
    "close": 389500.0,
    "volume": 206515.0
  },
  {
    "time": 1746543600,
    "open": 395000.0,
    "high": 409000.0,
    "low": 374500.0,
    "close": 401500.0,
    "volume": 188441.0
  },
  {
    "time": 1746975600,
    "open": 409000.0,
    "high": 438000.0,
    "low": 370000.0,
    "close": 416000.0,
    "volume": 506420.0
  },
  {
    "time": 1747580400,
    "open": 416000.0,
    "high": 450500.0,
    "low": 409500.0,
    "close": 450000.0,
    "volume": 337224.0
  },
  {
    "time": 1748185200,
    "open": 450000.0,
    "high": 454500.0,
    "low": 430500.0,
    "close": 451000.0,
    "volume": 329246.0
  },
  {
    "time": 1748790000,
    "open": 457000.0,
    "high": 499000.0,
    "low": 455500.0,
    "close": 479000.0,
    "volume": 241615.0
  },
  {
    "time": 1749394800,
    "open": 476000.0,
    "high": 534000.0,
    "low": 431000.0,
    "close": 433500.0,
    "volume": 1245463.0
  },
  {
    "time": 1749999600,
    "open": 450000.0,
    "high": 476000.0,
    "low": 418000.0,
    "close": 457000.0,
    "volume": 1358809.0
  },
  {
    "time": 1750604400,
    "open": 447500.0,
    "high": 502000.0,
    "low": 446000.0,
    "close": 485500.0,
    "volume": 646191.0
  },
  {
    "time": 1751209200,
    "open": 487000.0,
    "high": 518000.0,
    "low": 460000.0,
    "close": 492500.0,
    "volume": 637329.0
  },
  {
    "time": 1751814000,
    "open": 505000.0,
    "high": 597000.0,
    "low": 496500.0,
    "close": 561000.0,
    "volume": 1022368.0
  },
  {
    "time": 1752418800,
    "open": 566000.0,
    "high": 600000.0,
    "low": 560000.0,
    "close": 567000.0,
    "volume": 386121.0
  },
  {
    "time": 1753023600,
    "open": 565000.0,
    "high": 591000.0,
    "low": 556000.0,
    "close": 558000.0,
    "volume": 345307.0
  },
  {
    "time": 1753628400,
    "open": 550000.0,
    "high": 567000.0,
    "low": 525000.0,
    "close": 551000.0,
    "volume": 392084.0
  },
  {
    "time": 1754233200,
    "open": 542000.0,
    "high": 678000.0,
    "low": 537000.0,
    "close": 664000.0,
    "volume": 639621.0
  },
  {
    "time": 1754838000,
    "open": 665000.0,
    "high": 698000.0,
    "low": 656000.0,
    "close": 684000.0,
    "volume": 396579.0
  },
  {
    "time": 1755442800,
    "open": 687000.0,
    "high": 703000.0,
    "low": 631000.0,
    "close": 700000.0,
    "volume": 348226.0
  },
  {
    "time": 1756047600,
    "open": 696000.0,
    "high": 713000.0,
    "low": 660000.0,
    "close": 680000.0,
    "volume": 310576.0
  },
  {
    "time": 1756652400,
    "open": 680000.0,
    "high": 685000.0,
    "low": 622000.0,
    "close": 630000.0,
    "volume": 348802.0
  },
  {
    "time": 1757257200,
    "open": 641000.0,
    "high": 696000.0,
    "low": 618000.0,
    "close": 644000.0,
    "volume": 657168.0
  },
  {
    "time": 1757862000,
    "open": 631000.0,
    "high": 635000.0,
    "low": 609500.0,
    "close": 626000.0,
    "volume": 142521.0
  }
]