[
  {
    "time": 1696431600,
    "open": 59100.0,
    "high": 67600.0,
    "low": 32150.0,
    "close": 37250.0,
    "volume": 67816707.0
  },
  {
    "time": 1698764400,
    "open": 37250.0,
    "high": 94700.0,
    "low": 37250.0,
    "close": 92900.0,
    "volume": 120617149.0
  },
  {
    "time": 1701356400,
    "open": 95100.0,
    "high": 124500.0,
    "low": 76900.0,
    "close": 116100.0,
    "volume": 78845988.0
  },
  {
    "time": 1704121200,
    "open": 116100.0,
    "high": 116800.0,
    "low": 68700.0,
    "close": 68700.0,
    "volume": 34636345.0
  },
  {
    "time": 1706713200,
    "open": 69700.0,
    "high": 86300.0,
    "low": 67300.0,
    "close": 73900.0,
    "volume": 24375794.0
  },
  {
    "time": 1709478000,
    "open": 74400.0,
    "high": 95900.0,
    "low": 74200.0,
    "close": 88200.0,
    "volume": 26219448.0
  },
  {
    "time": 1711897200,
    "open": 88500.0,
    "high": 88800.0,
    "low": 69100.0,
    "close": 72000.0,
    "volume": 11231921.0
  },
  {
    "time": 1714575600,
    "open": 72400.0,
    "high": 76800.0,
    "low": 71500.0,
    "close": 72400.0,
    "volume": 5878442.0
  },
  {
    "time": 1717340400,
    "open": 72500.0,
    "high": 90800.0,
    "low": 72200.0,
    "close": 79900.0,
    "volume": 19571205.0
  },
  {
    "time": 1719759600,
    "open": 80000.0,
    "high": 109300.0,
    "low": 71000.0,
    "close": 71200.0,
    "volume": 43542222.0
  },
  {
    "time": 1722438000,
    "open": 71500.0,
    "high": 73600.0,
    "low": 53900.0,
    "close": 70400.0,
    "volume": 7825496.0
  },
  {
    "time": 1725202800,
    "open": 69700.0,
    "high": 70100.0,
    "low": 61200.0,
    "close": 63700.0,
    "volume": 3511939.0
  },
  {
    "time": 1727794800,
    "open": 62100.0,
    "high": 78200.0,
    "low": 58400.0,
    "close": 70200.0,
    "volume": 9482289.0
  },
  {
    "time": 1730386800,
    "open": 69000.0,
    "high": 75500.0,
    "low": 60600.0,
    "close": 64800.0,
    "volume": 6584815.0
  },
  {
    "time": 1733065200,
    "open": 66800.0,
    "high": 67100.0,
    "low": 49850.0,
    "close": 52300.0,
    "volume": 9615295.0
  },
  {
    "time": 1735743600,
    "open": 56600.0,
    "high": 68600.0,
    "low": 56200.0,
    "close": 67000.0,
    "volume": 15192345.0
  },
  {
    "time": 1738508400,
    "open": 66000.0,
    "high": 77000.0,
    "low": 63100.0,
    "close": 63100.0,
    "volume": 18875117.0
  },
  {
    "time": 1741014000,
    "open": 62100.0,
    "high": 65000.0,
    "low": 50000.0,
    "close": 50200.0,
    "volume": 4490950.0
  },
  {
    "time": 1743433200,
    "open": 50600.0,
    "high": 56900.0,
    "low": 39550.0,
    "close": 50400.0,
    "volume": 6345226.0
  },
  {
    "time": 1746111600,
    "open": 49850.0,
    "high": 52900.0,
    "low": 45750.0,
    "close": 47200.0,
    "volume": 3444626.0
  },
  {
    "time": 1748790000,
    "open": 47250.0,
    "high": 70900.0,
    "low": 46700.0,
    "close": 66100.0,
    "volume": 12689398.0
  },
  {
    "time": 1751295600,
    "open": 67300.0,
    "high": 67300.0,
    "low": 58700.0,
    "close": 60400.0,
    "volume": 4815394.0
  },
  {
    "time": 1753974000,
    "open": 59500.0,
    "high": 66000.0,
    "low": 57400.0,
    "close": 62500.0,
    "volume": 4691301.0
  },
  {
    "time": 1756652400,
    "open": 63300.0,
    "high": 66500.0,
    "low": 60300.0,
    "close": 64600.0,
    "volume": 2553135.0
  }
]