[
  {
    "time": 1490194800,
    "open": 26000.0,
    "high": 30000.0,
    "low": 18250.0,
    "close": 18250.0,
    "volume": 12623574.0
  },
  {
    "time": 1491145200,
    "open": 18350.0,
    "high": 19850.0,
    "low": 16100.0,
    "close": 17950.0,
    "volume": 5473634.0
  },
  {
    "time": 1493650800,
    "open": 18100.0,
    "high": 20950.0,
    "low": 17950.0,
    "close": 20450.0,
    "volume": 3107473.0
  },
  {
    "time": 1496242800,
    "open": 20450.0,
    "high": 25850.0,
    "low": 19600.0,
    "close": 23900.0,
    "volume": 6769490.0
  },
  {
    "time": 1499007600,
    "open": 24100.0,
    "high": 27350.0,
    "low": 22000.0,
    "close": 24350.0,
    "volume": 5421962.0
  },
  {
    "time": 1501513200,
    "open": 24400.0,
    "high": 26250.0,
    "low": 22900.0,
    "close": 23700.0,
    "volume": 2548002.0
  },
  {
    "time": 1504191600,
    "open": 23700.0,
    "high": 24150.0,
    "low": 21750.0,
    "close": 22500.0,
    "volume": 1498505.0
  },
  {
    "time": 1507561200,
    "open": 22850.0,
    "high": 24500.0,
    "low": 22000.0,
    "close": 23700.0,
    "volume": 928342.0
  },
  {
    "time": 1509462000,
    "open": 24000.0,
    "high": 29550.0,
    "low": 23400.0,
    "close": 27500.0,
    "volume": 7648609.0
  },
  {
    "time": 1512054000,
    "open": 27800.0,
    "high": 28650.0,
    "low": 24000.0,
    "close": 25650.0,
    "volume": 1714628.0
  },
  {
    "time": 1514818800,
    "open": 25550.0,
    "high": 25800.0,
    "low": 22900.0,
    "close": 24300.0,
    "volume": 2069649.0
  },
  {
    "time": 1517410800,
    "open": 24250.0,
    "high": 28400.0,
    "low": 21450.0,
    "close": 27900.0,
    "volume": 1836596.0
  },
  {
    "time": 1519916400,
    "open": 27600.0,
    "high": 32850.0,
    "low": 26750.0,
    "close": 30300.0,
    "volume": 2164831.0
  },
  {
    "time": 1522594800,
    "open": 30700.0,
    "high": 39000.0,
    "low": 28800.0,
    "close": 38000.0,
    "volume": 3160821.0
  },
  {
    "time": 1525186800,
    "open": 37600.0,
    "high": 38450.0,
    "low": 30950.0,
    "close": 32700.0,
    "volume": 1722560.0
  },
  {
    "time": 1527778800,
    "open": 32600.0,
    "high": 32600.0,
    "low": 27100.0,
    "close": 28450.0,
    "volume": 1284005.0
  },
  {
    "time": 1530457200,
    "open": 28000.0,
    "high": 33200.0,
    "low": 26350.0,
    "close": 32150.0,
    "volume": 1370867.0
  },
  {
    "time": 1533049200,
    "open": 32100.0,
    "high": 32950.0,
    "low": 28850.0,
    "close": 30600.0,
    "volume": 771219.0
  },
  {
    "time": 1535900400,
    "open": 30650.0,
    "high": 31650.0,
    "low": 28400.0,
    "close": 29050.0,
    "volume": 657220.0
  },
  {
    "time": 1538319600,
    "open": 28700.0,
    "high": 29500.0,
    "low": 22000.0,
    "close": 24100.0,
    "volume": 833477.0
  },
  {
    "time": 1540998000,
    "open": 24100.0,
    "high": 25150.0,
    "low": 20550.0,
    "close": 21700.0,
    "volume": 591621.0
  },
  {
    "time": 1543762800,
    "open": 21750.0,
    "high": 23000.0,
    "low": 19350.0,
    "close": 21350.0,
    "volume": 501299.0
  },
  {
    "time": 1546354800,
    "open": 21350.0,
    "high": 25450.0,
    "low": 19250.0,
    "close": 24700.0,
    "volume": 613301.0
  },
  {
    "time": 1548946800,
    "open": 24750.0,
    "high": 29600.0,
    "low": 24200.0,
    "close": 27300.0,
    "volume": 829155.0
  },
  {
    "time": 1551625200,
    "open": 27300.0,
    "high": 28750.0,
    "low": 24350.0,
    "close": 25150.0,
    "volume": 442946.0
  },
  {
    "time": 1554044400,
    "open": 25800.0,
    "high": 29200.0,
    "low": 25500.0,
    "close": 27400.0,
    "volume": 437646.0
  },
  {
    "time": 1556722800,
    "open": 27400.0,
    "high": 31100.0,
    "low": 25750.0,
    "close": 28000.0,
    "volume": 932458.0
  },
  {
    "time": 1559487600,
    "open": 28000.0,
    "high": 30100.0,
    "low": 26450.0,
    "close": 27200.0,
    "volume": 693339.0
  },
  {
    "time": 1561906800,
    "open": 27600.0,
    "high": 27650.0,
    "low": 24000.0,
    "close": 26350.0,
    "volume": 599366.0
  },
  {
    "time": 1564585200,
    "open": 26050.0,
    "high": 26450.0,
    "low": 23000.0,
    "close": 25350.0,
    "volume": 375103.0
  },
  {
    "time": 1567350000,
    "open": 25550.0,
    "high": 27100.0,
    "low": 23600.0,
    "close": 23800.0,
    "volume": 449175.0
  },
  {
    "time": 1569855600,
    "open": 23900.0,
    "high": 28900.0,
    "low": 23700.0,
    "close": 28450.0,
    "volume": 519662.0
  },
  {
    "time": 1572534000,
    "open": 28450.0,
    "high": 29100.0,
    "low": 24500.0,
    "close": 24800.0,
    "volume": 399728.0
  },
  {
    "time": 1575212400,
    "open": 24850.0,
    "high": 28100.0,
    "low": 23300.0,
    "close": 27900.0,
    "volume": 414584.0
  },
  {
    "time": 1577890800,
    "open": 27800.0,
    "high": 31300.0,
    "low": 26500.0,
    "close": 27100.0,
    "volume": 937478.0
  },
  {
    "time": 1580655600,
    "open": 27100.0,
    "high": 31950.0,
    "low": 26350.0,
    "close": 28250.0,
    "volume": 1284764.0
  },
  {
    "time": 1583074800,
    "open": 28500.0,
    "high": 32400.0,
    "low": 16500.0,
    "close": 24050.0,
    "volume": 1639229.0
  },
  {
    "time": 1585666800,
    "open": 23850.0,
    "high": 26250.0,
    "low": 22000.0,
    "close": 24900.0,
    "volume": 826229.0
  },
  {
    "time": 1588518000,
    "open": 24400.0,
    "high": 38500.0,
    "low": 23950.0,
    "close": 32400.0,
    "volume": 3288203.0
  },
  {
    "time": 1590937200,
    "open": 33800.0,
    "high": 40650.0,
    "low": 30300.0,
    "close": 35950.0,
    "volume": 3540975.0
  },
  {
    "time": 1593529200,
    "open": 36500.0,
    "high": 42750.0,
    "low": 34800.0,
    "close": 39500.0,
    "volume": 3301711.0
  },
  {
    "time": 1596380400,
    "open": 39500.0,
    "high": 41200.0,
    "low": 34350.0,
    "close": 38650.0,
    "volume": 2121700.0
  },
  {
    "time": 1598886000,
    "open": 39000.0,
    "high": 45400.0,
    "low": 35750.0,
    "close": 38100.0,
    "volume": 1961502.0
  },
  {
    "time": 1601823600,
    "open": 38450.0,
    "high": 39750.0,
    "low": 32800.0,
    "close": 36650.0,
    "volume": 913642.0
  },
  {
    "time": 1604242800,
    "open": 36650.0,
    "high": 44500.0,
    "low": 36000.0,
    "close": 43150.0,
    "volume": 1885850.0
  },
  {
    "time": 1606748400,
    "open": 43200.0,
    "high": 51200.0,
    "low": 42650.0,
    "close": 49950.0,
    "volume": 1498663.0
  },
  {
    "time": 1609686000,
    "open": 50600.0,
    "high": 66900.0,
    "low": 46000.0,
    "close": 54000.0,
    "volume": 2403851.0
  },
  {
    "time": 1612105200,
    "open": 54000.0,
    "high": 66600.0,
    "low": 54000.0,
    "close": 58000.0,
    "volume": 1441797.0
  },
  {
    "time": 1614610800,
    "open": 59400.0,
    "high": 70500.0,
    "low": 51600.0,
    "close": 64200.0,
    "volume": 1304854.0
  },
  {
    "time": 1617202800,
    "open": 65300.0,
    "high": 75000.0,
    "low": 63100.0,
    "close": 64400.0,
    "volume": 2147618.0
  },
  {
    "time": 1619967600,
    "open": 64400.0,
    "high": 70800.0,
    "low": 60700.0,
    "close": 68000.0,
    "volume": 1764623.0
  },
  {
    "time": 1622473200,
    "open": 68000.0,
    "high": 71400.0,
    "low": 64500.0,
    "close": 70100.0,
    "volume": 897102.0
  },
  {
    "time": 1625065200,
    "open": 70700.0,
    "high": 70700.0,
    "low": 62300.0,
    "close": 65200.0,
    "volume": 742306.0
  },
  {
    "time": 1627830000,
    "open": 65300.0,
    "high": 88400.0,
    "low": 64700.0,
    "close": 82600.0,
    "volume": 2431811.0
  },
  {
    "time": 1630422000,
    "open": 82100.0,
    "high": 90900.0,
    "low": 74300.0,
    "close": 76400.0,
    "volume": 788872.0
  },
  {
    "time": 1633014000,
    "open": 75900.0,
    "high": 83000.0,
    "low": 71000.0,
    "close": 81600.0,
    "volume": 523749.0
  },
  {
    "time": 1635692400,
    "open": 81400.0,
    "high": 86000.0,
    "low": 66200.0,
    "close": 66400.0,
    "volume": 1539028.0
  },
  {
    "time": 1638284400,
    "open": 67500.0,
    "high": 74300.0,
    "low": 60900.0,
    "close": 67100.0,
    "volume": 1898392.0
  },
  {
    "time": 1641135600,
    "open": 67100.0,
    "high": 67300.0,
    "low": 53800.0,
    "close": 55900.0,
    "volume": 948103.0
  },
  {
    "time": 1643814000,
    "open": 57500.0,
    "high": 58600.0,
    "low": 50500.0,
    "close": 53900.0,
    "volume": 738821.0
  },
  {
    "time": 1646146800,
    "open": 53900.0,
    "high": 61300.0,
    "low": 49400.0,
    "close": 60200.0,
    "volume": 864748.0
  },
  {
    "time": 1648738800,
    "open": 59000.0,
    "high": 65600.0,
    "low": 52400.0,
    "close": 54800.0,
    "volume": 2709261.0
  },
  {
    "time": 1651417200,
    "open": 53800.0,
    "high": 64000.0,
    "low": 53300.0,
    "close": 60700.0,
    "volume": 1736516.0
  },
  {
    "time": 1654095600,
    "open": 60500.0,
    "high": 61700.0,
    "low": 46500.0,
    "close": 46950.0,
    "volume": 850197.0
  },
  {
    "time": 1656601200,
    "open": 47150.0,
    "high": 52200.0,
    "low": 43100.0,
    "close": 51400.0,
    "volume": 696673.0
  },
  {
    "time": 1659279600,
    "open": 51200.0,
    "high": 51500.0,
    "low": 42900.0,
    "close": 46750.0,
    "volume": 862089.0
  },
  {
    "time": 1661958000,
    "open": 46100.0,
    "high": 52700.0,
    "low": 39250.0,
    "close": 39850.0,
    "volume": 781335.0
  },
  {
    "time": 1664809200,
    "open": 41100.0,
    "high": 51900.0,
    "low": 41100.0,
    "close": 46500.0,
    "volume": 724607.0
  },
  {
    "time": 1667228400,
    "open": 45800.0,
    "high": 53500.0,
    "low": 43550.0,
    "close": 47250.0,
    "volume": 852680.0
  },
  {
    "time": 1669820400,
    "open": 48800.0,
    "high": 49250.0,
    "low": 42250.0,
    "close": 43100.0,
    "volume": 675359.0
  },
  {
    "time": 1672585200,
    "open": 43150.0,
    "high": 48800.0,
    "low": 41600.0,
    "close": 47650.0,
    "volume": 523555.0
  },
  {
    "time": 1675177200,
    "open": 47700.0,
    "high": 49300.0,
    "low": 44050.0,
    "close": 45700.0,
    "volume": 893816.0
  },
  {
    "time": 1677682800,
    "open": 45700.0,
    "high": 51900.0,
    "low": 41850.0,
    "close": 50300.0,
    "volume": 1192875.0
  },
  {
    "time": 1680447600,
    "open": 50300.0,
    "high": 50300.0,
    "low": 42650.0,
    "close": 43500.0,
    "volume": 819560.0
  },
  {
    "time": 1682953200,
    "open": 43450.0,
    "high": 54100.0,
    "low": 41550.0,
    "close": 52100.0,
    "volume": 1108917.0
  },
  {
    "time": 1685545200,
    "open": 50500.0,
    "high": 64000.0,
    "low": 50400.0,
    "close": 61700.0,
    "volume": 1921624.0
  },
  {
    "time": 1688310000,
    "open": 61800.0,
    "high": 66300.0,
    "low": 55300.0,
    "close": 60800.0,
    "volume": 1849020.0
  },
  {
    "time": 1690815600,
    "open": 61500.0,
    "high": 61500.0,
    "low": 51900.0,
    "close": 54100.0,
    "volume": 1052425.0
  },
  {
    "time": 1693494000,
    "open": 54100.0,
    "high": 57400.0,
    "low": 47000.0,
    "close": 48700.0,
    "volume": 1219598.0
  },
  {
    "time": 1696345200,
    "open": 47650.0,
    "high": 51800.0,
    "low": 44200.0,
    "close": 44250.0,
    "volume": 781653.0
  },
  {
    "time": 1698764400,
    "open": 44700.0,
    "high": 61200.0,
    "low": 44350.0,
    "close": 60400.0,
    "volume": 1974562.0
  },
  {
    "time": 1701356400,
    "open": 60400.0,
    "high": 67400.0,
    "low": 57200.0,
    "close": 64500.0,
    "volume": 1701154.0
  },
  {
    "time": 1704121200,
    "open": 63900.0,
    "high": 68900.0,
    "low": 59700.0,
    "close": 61000.0,
    "volume": 1724611.0
  },
  {
    "time": 1706713200,
    "open": 61300.0,
    "high": 63700.0,
    "low": 56000.0,
    "close": 61900.0,
    "volume": 1584610.0
  },
  {
    "time": 1709478000,
    "open": 63500.0,
    "high": 75800.0,
    "low": 57600.0,
    "close": 74600.0,
    "volume": 3753528.0
  },
  {
    "time": 1711897200,
    "open": 75100.0,
    "high": 93000.0,
    "low": 70500.0,
    "close": 91500.0,
    "volume": 3937984.0
  },
  {
    "time": 1714575600,
    "open": 89700.0,
    "high": 98400.0,
    "low": 84500.0,
    "close": 86200.0,
    "volume": 3294701.0
  },
  {
    "time": 1717340400,
    "open": 86300.0,
    "high": 91800.0,
    "low": 77900.0,
    "close": 80300.0,
    "volume": 2480420.0
  },
  {
    "time": 1719759600,
    "open": 79700.0,
    "high": 87700.0,
    "low": 70300.0,
    "close": 75000.0,
    "volume": 2365681.0
  },
  {
    "time": 1722438000,
    "open": 77200.0,
    "high": 77700.0,
    "low": 59300.0,
    "close": 67700.0,
    "volume": 2847084.0
  },
  {
    "time": 1725202800,
    "open": 67700.0,
    "high": 67700.0,
    "low": 54200.0,
    "close": 57500.0,
    "volume": 1655694.0
  },
  {
    "time": 1727794800,
    "open": 56500.0,
    "high": 59200.0,
    "low": 46950.0,
    "close": 50800.0,
    "volume": 1476028.0
  },
  {
    "time": 1730386800,
    "open": 49950.0,
    "high": 50300.0,
    "low": 36100.0,
    "close": 36500.0,
    "volume": 2317602.0
  },
  {
    "time": 1733065200,
    "open": 36900.0,
    "high": 38550.0,
    "low": 31550.0,
    "close": 36600.0,
    "volume": 1668958.0
  },
  {
    "time": 1735743600,
    "open": 36350.0,
    "high": 45850.0,
    "low": 36150.0,
    "close": 37900.0,
    "volume": 2727446.0
  },
  {
    "time": 1738508400,
    "open": 36650.0,
    "high": 49900.0,
    "low": 35700.0,
    "close": 43850.0,
    "volume": 4208573.0
  },
  {
    "time": 1741014000,
    "open": 43500.0,
    "high": 61800.0,
    "low": 39550.0,
    "close": 56000.0,
    "volume": 4774926.0
  },
  {
    "time": 1743433200,
    "open": 56200.0,
    "high": 65500.0,
    "low": 50300.0,
    "close": 58700.0,
    "volume": 3633998.0
  },
  {
    "time": 1746111600,
    "open": 59100.0,
    "high": 64000.0,
    "low": 54200.0,
    "close": 57700.0,
    "volume": 1751877.0
  },
  {
    "time": 1748790000,
    "open": 57300.0,
    "high": 80000.0,
    "low": 56300.0,
    "close": 72300.0,
    "volume": 2750709.0
  },
  {
    "time": 1751295600,
    "open": 72800.0,
    "high": 75500.0,
    "low": 59200.0,
    "close": 70800.0,
    "volume": 3519015.0
  },
  {
    "time": 1753974000,
    "open": 68200.0,
    "high": 85300.0,
    "low": 64300.0,
    "close": 82500.0,
    "volume": 3384967.0
  },
  {
    "time": 1756652400,
    "open": 79400.0,
    "high": 89900.0,
    "low": 79000.0,
    "close": 87900.0,
    "volume": 789718.0
  }
]